[
    {
        "name": "LMAnime (ALL)",
        "results": {
            "popular": {
                "result": [
                    {
                        "animes": [
                            {
                                "url": "/the-magic-chef-of-ice-and-fire/",
                                "title": "The Magic Chef Of Ice And Fire",
                                "thumbnail_url": "https://lmanime.com/wp-content/uploads/2022/08/The-Magic-Chef-Of-Ice-And-Fire.jpg"
                            },
                            {
                                "url": "/soul-land-douluo-dalu-season-2-temporary/",
                                "title": "Soul Land (Douluo Dalu) Season 2 {temporary}",
                                "thumbnail_url": "https://lmanime.com/wp-content/uploads/2022/08/2021-11-13-768x1077.jpg"
                            },
                            {
                                "url": "/the-legend-of-sword-domain/",
                                "title": "The Legend Of Sword Domain",
                                "thumbnail_url": "https://lmanime.com/wp-content/uploads/2022/08/The-Legend-Of-Sword-Domain.jpg"
                            },
                            {
                                "url": "/the-peak-of-true-martial-arts/",
                                "title": "The Peak Of True Martial Arts",
                                "thumbnail_url": "https://lmanime.com/wp-content/uploads/2022/08/unnamed-1-3.jpg"
                            },
                            {
                                "url": "/throne-of-seal/",
                                "title": "Throne of Seal",
                                "thumbnail_url": "https://lmanime.com/wp-content/uploads/2022/08/Throne-of-Seal.png"
                            },
                            {
                                "url": "/the-success-of-empyrean-xuan-emperor-season-3/",
                                "title": "The Success of Empyrean Xuan Emperor Season 3",
                                "thumbnail_url": "https://lmanime.com/wp-content/uploads/2022/11/The-Success-of-Empyrean-Xuan-Emperor-Season.jpg"
                            },
                            {
                                "url": "/one-hundred-thousand-years-of-qi-refining/",
                                "title": "One Hundred Thousand Years of Qi Refining",
                                "thumbnail_url": "https://lmanime.com/wp-content/uploads/2023/03/One-Hundred-Thousand-Years-of-Qi-Refining.jpg"
                            },
                            {
                                "url": "/a-record-of-a-mortals-journey-to-immortality-season-02/",
                                "title": "A Record of A Mortal’s Journey to Immortality Season 02",
                                "thumbnail_url": "https://lmanime.com/wp-content/uploads/2022/08/0-1-768x1024-1.jpg"
                            },
                            {
                                "url": "/a-record-of-a-mortals-journey-to-immortality-season-03/",
                                "title": "A Record of A Mortal’s Journey to Immortality Season 03",
                                "thumbnail_url": "https://lmanime.com/wp-content/uploads/2023/08/IMM.jpg"
                            },
                            {
                                "url": "/apotheosis/",
                                "title": "Apotheosis",
                                "thumbnail_url": "https://lmanime.com/wp-content/uploads/2022/11/AP-1.jpg"
                            },
                            {
                                "url": "/apotheosis-temporary/",
                                "title": "Apotheosis (Temporary)",
                                "thumbnail_url": "https://lmanime.com/wp-content/uploads/2024/04/ap.jpg"
                            },
                            {
                                "url": "/legend-of-xianwu/",
                                "title": "Legend of Xianwu",
                                "thumbnail_url": "https://lmanime.com/wp-content/uploads/2023/03/Legend-of-Xianwu-1-768x1365.jpg"
                            },
                            {
                                "url": "/war-god-system-im-counting-on-you/",
                                "title": "War God System! I’m Counting On You!",
                                "thumbnail_url": "https://lmanime.com/wp-content/uploads/2022/08/unnamed-1-1-2.jpg"
                            },
                            {
                                "url": "/the-success-of-empyrean-xuan-emperor-season-2/",
                                "title": "The Success of Empyrean Xuan Emperor Season 2",
                                "thumbnail_url": "https://lmanime.com/wp-content/uploads/2022/08/2022-05-01-1-768x1074.jpg"
                            },
                            {
                                "url": "/the-land-of-miracles/",
                                "title": "The Land of Miracles",
                                "thumbnail_url": "https://lmanime.com/wp-content/uploads/2022/08/The-Land-of-Miracles.jpg"
                            },
                            {
                                "url": "/rise-of-the-dragon/",
                                "title": "Rise of the Dragon",
                                "thumbnail_url": "https://lmanime.com/wp-content/uploads/2022/08/2022-07-01-768x1140.jpg"
                            },
                            {
                                "url": "/the-galaxy-emperor/",
                                "title": "The Galaxy Emperor",
                                "thumbnail_url": "https://lmanime.com/wp-content/uploads/2023/08/The-Galaxy-Emperor.jpg"
                            },
                            {
                                "url": "/leveling-up-in-a-fantasy-world/",
                                "title": "Leveling up in a Fantasy World",
                                "thumbnail_url": "https://lmanime.com/wp-content/uploads/2022/11/Leveling-up-in-a-Fantasy-World.jpg"
                            },
                            {
                                "url": "/supreme-god-emperor-season-02/",
                                "title": "Supreme God Emperor Season 02",
                                "thumbnail_url": "https://lmanime.com/wp-content/uploads/2022/08/download_20210520_110043-768x1365.jpg"
                            },
                            {
                                "url": "/the-success-of-empyrean-xuan-emperor-season-5/",
                                "title": "The Success of Empyrean Xuan Emperor Season 5",
                                "thumbnail_url": "https://lmanime.com/wp-content/uploads/2023/11/XUAN-E5.jpg"
                            }
                        ],
                        "hasNextPage": true
                    }
                ],
                "passed": true
            },
            "latest": {
                "result": [
                    {
                        "animes": [
                            {
                                "url": "/apotheosis/",
                                "title": "Apotheosis",
                                "thumbnail_url": "https://lmanime.com/wp-content/uploads/2022/11/AP-1.jpg"
                            },
                            {
                                "url": "/jade-dynasty/",
                                "title": "Jade Dynasty",
                                "thumbnail_url": "https://lmanime.com/wp-content/uploads/2022/08/Jade-Dynasty.jpg"
                            },
                            {
                                "url": "/glorious-revenge-of-ye-feng/",
                                "title": "Glorious Revenge of Ye Feng",
                                "thumbnail_url": "https://lmanime.com/wp-content/uploads/2023/09/Glorious-Revenge-of-Ye-Feng.jpg"
                            },
                            {
                                "url": "/the-magic-chef-of-ice-and-fire/",
                                "title": "The Magic Chef Of Ice And Fire",
                                "thumbnail_url": "https://lmanime.com/wp-content/uploads/2022/08/The-Magic-Chef-Of-Ice-And-Fire.jpg"
                            },
                            {
                                "url": "/the-peak-of-true-martial-arts/",
                                "title": "The Peak Of True Martial Arts",
                                "thumbnail_url": "https://lmanime.com/wp-content/uploads/2022/08/unnamed-1-3.jpg"
                            },
                            {
                                "url": "/glorious-revenge-of-ye-feng-temporary/",
                                "title": "Glorious Revenge of Ye Feng (Temporary)",
                                "thumbnail_url": "https://lmanime.com/wp-content/uploads/2024/04/groyf.jpg"
                            },
                            {
                                "url": "/the-success-of-empyrean-xuan-emperor-season-5/",
                                "title": "The Success of Empyrean Xuan Emperor Season 5",
                                "thumbnail_url": "https://lmanime.com/wp-content/uploads/2023/11/XUAN-E5.jpg"
                            },
                            {
                                "url": "/apotheosis-temporary/",
                                "title": "Apotheosis (Temporary)",
                                "thumbnail_url": "https://lmanime.com/wp-content/uploads/2024/04/ap.jpg"
                            },
                            {
                                "url": "/the-great-ruler-temporary/",
                                "title": "The Great Ruler (temporary)",
                                "thumbnail_url": "https://lmanime.com/wp-content/uploads/2024/04/TGR.jpg"
                            },
                            {
                                "url": "/legend-of-xianwu/",
                                "title": "Legend of Xianwu",
                                "thumbnail_url": "https://lmanime.com/wp-content/uploads/2023/03/Legend-of-Xianwu-1-768x1365.jpg"
                            },
                            {
                                "url": "/big-brother/",
                                "title": "Big Brother",
                                "thumbnail_url": "https://lmanime.com/wp-content/uploads/2023/08/A-MORTAL.jpg"
                            },
                            {
                                "url": "/big-brother-temporary/",
                                "title": "Big Brother (Temporary)",
                                "thumbnail_url": "https://lmanime.com/wp-content/uploads/2024/04/Screenshot_20240404-185412-768x1024.png"
                            },
                            {
                                "url": "/the-legend-of-sword-domain/",
                                "title": "The Legend Of Sword Domain",
                                "thumbnail_url": "https://lmanime.com/wp-content/uploads/2022/08/The-Legend-Of-Sword-Domain.jpg"
                            },
                            {
                                "url": "/the-secrets-of-star-divine-arts/",
                                "title": "The Secrets of Star Divine Arts",
                                "thumbnail_url": "https://lmanime.com/wp-content/uploads/2024/01/The-Secrets-of-Star-Divine-Arts.jpg"
                            },
                            {
                                "url": "/the-age-of-cosmos-exploration/",
                                "title": "The Age of Cosmos Exploration",
                                "thumbnail_url": "https://lmanime.com/wp-content/uploads/2024/02/The-Age-of-Cosmos-Exploration.jpg"
                            },
                            {
                                "url": "/lord-of-all-lords/",
                                "title": "Lord of All Lords",
                                "thumbnail_url": "https://lmanime.com/wp-content/uploads/2024/01/1000013681-768x1365.jpg"
                            },
                            {
                                "url": "/the-proud-emperor-of-eternity/",
                                "title": "The Proud Emperor of Eternity",
                                "thumbnail_url": "https://lmanime.com/wp-content/uploads/2024/01/The-Proud-Emperor-of-Eternity.jpg"
                            },
                            {
                                "url": "/soul-land-2-the-peerless-tang-clan/",
                                "title": "Soul Land 2: The Peerless Tang Clan",
                                "thumbnail_url": "https://lmanime.com/wp-content/uploads/2023/06/unnamed-2.jpg"
                            },
                            {
                                "url": "/a-record-of-a-mortals-journey-to-immortality-season-03/",
                                "title": "A Record of A Mortal’s Journey to Immortality Season 03",
                                "thumbnail_url": "https://lmanime.com/wp-content/uploads/2023/08/IMM.jpg"
                            },
                            {
                                "url": "/blader-soul/",
                                "title": "Blader Soul",
                                "thumbnail_url": "https://lmanime.com/wp-content/uploads/2024/03/bs.jpg"
                            }
                        ],
                        "hasNextPage": true
                    }
                ],
                "passed": true
            },
            "search": {
                "result": [
                    {
                        "animes": [
                            {
                                "url": "/otherworldly-evil-monarch/",
                                "title": "Otherworldly Evil Monarch",
                                "thumbnail_url": "https://lmanime.com/wp-content/uploads/2024/02/Otherworldly-Evil-Monarch.jpg"
                            },
                            {
                                "url": "/leveling-up-in-a-fantasy-world/",
                                "title": "Leveling up in a Fantasy World",
                                "thumbnail_url": "https://lmanime.com/wp-content/uploads/2022/11/Leveling-up-in-a-Fantasy-World.jpg"
                            },
                            {
                                "url": "/perfect-world-temporary/",
                                "title": "Perfect World [ Temporary ]",
                                "thumbnail_url": "https://lmanime.com/wp-content/uploads/2022/08/Perfect-World-1.jpg"
                            },
                            {
                                "url": "/perfect-world/",
                                "title": "Perfect World",
                                "thumbnail_url": "https://lmanime.com/wp-content/uploads/2022/08/Perfect-World.jpg"
                            },
                            {
                                "url": "/my-journey-in-an-alternate-world/",
                                "title": "My Journey In An Alternate World",
                                "thumbnail_url": "https://lmanime.com/wp-content/uploads/2022/08/2022-01-15-1-768x1075.jpg"
                            },
                            {
                                "url": "/god-of-the-magical-world/",
                                "title": "God Of The Magical World",
                                "thumbnail_url": "https://lmanime.com/wp-content/uploads/2022/08/11-768x1365.jpg"
                            },
                            {
                                "url": "/different-world-medicine-shop-season-02/",
                                "title": "Different world medicine Shop Season 02",
                                "thumbnail_url": "https://lmanime.com/wp-content/uploads/2022/08/Different.World_.Medicine.Store_.Ep42.mp4_snapshot_06.34_2021.04.28_15.20.53-e1619624002992.jpg"
                            },
                            {
                                "url": "/different-world-medicine-shop-yi-shijie-zhongyao-pu/",
                                "title": "Different World Medicine Shop (Yi Shijie Zhongyao Pu)",
                                "thumbnail_url": "https://lmanime.com/wp-content/uploads/2022/08/1604994147-5852-108202.jpg"
                            },
                            {
                                "url": "/agents-in-otherworld/",
                                "title": "Agents in Otherworld",
                                "thumbnail_url": "https://lmanime.com/wp-content/uploads/2022/08/006WCj8Mgy1gr2tuvbc2wj30fi0ln0vz.jpg"
                            },
                            {
                                "url": "/a-world-worth-protecting/",
                                "title": "A World Worth Protecting",
                                "thumbnail_url": "https://lmanime.com/wp-content/uploads/2022/08/A-World-Worth-Protecting.jpg"
                            }
                        ],
                        "hasNextPage": true
                    }
                ],
                "passed": true
            },
            "details": {
                "result": {
                    "url": "/the-magic-chef-of-ice-and-fire/",
                    "title": "The Magic Chef Of Ice And Fire",
                    "artist": "Joicy Studio",
                    "author": "LITTLE MOMENTS ANIME & FREE SUBS",
                    "description": "Watch streaming The Magic Chef Of Ice And Fire English Subbed on LMANIME. You can also download free The Magic Chef Of Ice And Fire Eng Sub, don't forget to watch online streaming of various quality 720P 360P 240P 480P according to your connection to save internet quota, The Magic Chef Of Ice And Fire on LMANIME MP4 MKV hardsub softsub English subbed is already contained in the video.\n\nAlternative name(s): 冰火魔厨\nStatus: Ongoing\nNetwork: Youku\nStudio: Joicy Studio\nReleased: Dec 11, 2021\nDuration: 20 min. per ep.\nSeason: Fall 2021\nCountry: China\nType: TV\nEpisodes: 156\nFansub: LITTLE MOMENTS ANIME & FREE SUBS\nCensor: Censored\nPosted by: lmanime-admin\nReleased on: August 23, 2022\nUpdated on: April 6, 2024\n",
                    "genre": "Action, Adventure, Fantasy, Magic, Martial Arts",
                    "status": 1,
                    "status_name": "ONGOING",
                    "thumbnail_url": "https://lmanime.com/wp-content/uploads/2022/08/The-Magic-Chef-Of-Ice-And-Fire.jpg",
                    "initialized": true
                },
                "passed": true
            },
            "episodes": {
                "result": [
                    {
                        "url": "/the-magic-chef-of-ice-and-fire-episode-137/",
                        "name": "Episode 137",
                        "date_upload": 1712361600000,
                        "episode_number": 137.0,
                        "scanlator": "Sub"
                    },
                    {
                        "url": "/the-magic-chef-of-ice-and-fire-episode-136/",
                        "name": "Episode 136",
                        "date_upload": 1712016000000,
                        "episode_number": 136.0,
                        "scanlator": "Sub"
                    }
                ],
                "passed": true
            },
            "videos": {
                "result": [
                    {
                        "url": "https://vod.cf.dmcdn.net/sec2(HPm8j-80ISnrpqnhSgvcPMVVlvcNhDscE6uOGrNA0VaIy65c5SM4V5KQZKfWMftIEsEL3Jg29aWW89KNoFU9Mbjinka80M7HgE7G4Ly6NQyPqkRY8m1uE-RsPF3QWeUHFk9gsT_Agrjv8FMMqKOBLQ)/video/817/871/538178718_mp4_h264_aac_hd_7.m3u8#cell=cf",
                        "quality": "Dailymotion (English)720p",
                        "videoUrl": "https://vod.cf.dmcdn.net/sec2(HPm8j-80ISnrpqnhSgvcPMVVlvcNhDscE6uOGrNA0VaIy65c5SM4V5KQZKfWMftIEsEL3Jg29aWW89KNoFU9Mbjinka80M7HgE7G4Ly6NQyPqkRY8m1uE-RsPF3QWeUHFk9gsT_Agrjv8FMMqKOBLQ)/video/817/871/538178718_mp4_h264_aac_hd_7.m3u8#cell=cf",
                        "headers": {
                            "User-Agent": "Mozilla/5.0 (X11; Linux x86_64; rv:121.0) Gecko/20100101 Firefox/121.0",
                            "Accept": "*/*"
                        }
                    },
                    {
                        "url": "https://vod.cf.dmcdn.net/sec2(ktmRqv9L1bijzPU1lMa_6RAqxstYKsp2wThYC2Q-DLH0eIB0om7b0a1c0z2p5IaT7M6Viw5W06JyXzFhY9JzhJLiaHCbR1JPKuMuYIsyuJBzT_GEcAuZfJHjQF3awF-P1kzRnBKY6mH_A-eDgpsg6A)/video/627/871/538178726_mp4_h264_aac_hd_8.m3u8#cell=cf",
                        "quality": "Dailymotion (العَرَبِيَّة)720p",
                        "videoUrl": "https://vod.cf.dmcdn.net/sec2(ktmRqv9L1bijzPU1lMa_6RAqxstYKsp2wThYC2Q-DLH0eIB0om7b0a1c0z2p5IaT7M6Viw5W06JyXzFhY9JzhJLiaHCbR1JPKuMuYIsyuJBzT_GEcAuZfJHjQF3awF-P1kzRnBKY6mH_A-eDgpsg6A)/video/627/871/538178726_mp4_h264_aac_hd_8.m3u8#cell=cf",
                        "headers": {
                            "User-Agent": "Mozilla/5.0 (X11; Linux x86_64; rv:121.0) Gecko/20100101 Firefox/121.0",
                            "Accept": "*/*"
                        }
                    },
                    {
                        "url": "https://vod.cf.dmcdn.net/sec2(Jhz730G8YppXHBpje1oc5wmgJn31tdCf4I3Hj-ZYKWthKQwMUsYz1aHhFZ8KZZNYwowb6fiI_qtM67z5QyuUTzk3hxEA8I6WSiw7015oBHklCqIQYIcZM5fsve0JSsT5tpOAP0rB9eWb-G2TTuo_Rw)/video/237/871/538178732_mp4_h264_aac_hd_8.m3u8#cell=cf",
                        "quality": "Dailymotion (Türkçe)720p",
                        "videoUrl": "https://vod.cf.dmcdn.net/sec2(Jhz730G8YppXHBpje1oc5wmgJn31tdCf4I3Hj-ZYKWthKQwMUsYz1aHhFZ8KZZNYwowb6fiI_qtM67z5QyuUTzk3hxEA8I6WSiw7015oBHklCqIQYIcZM5fsve0JSsT5tpOAP0rB9eWb-G2TTuo_Rw)/video/237/871/538178732_mp4_h264_aac_hd_8.m3u8#cell=cf",
                        "headers": {
                            "User-Agent": "Mozilla/5.0 (X11; Linux x86_64; rv:121.0) Gecko/20100101 Firefox/121.0",
                            "Accept": "*/*"
                        }
                    },
                    {
                        "url": "https://vod.cf.dmcdn.net/sec2(zJfeLKS4hcIFUO91WW-ZCIkeOIxUHGs4wtcm3Cp2xkvbqYctIItB4dhQeXTQYOyO2xZivRR_iLwd44Q5ufi2gK5Tsy2yEVKPrO-WB0hpnnoCwmzBDpMSlRGsfGkkQ4LTzFW8SbS0ZMXZMSx0EUYFbA)/video/827/871/538178728_mp4_h264_aac_hd_6.m3u8#cell=cf",
                        "quality": "Dailymotion (ไทย)720p",
                        "videoUrl": "https://vod.cf.dmcdn.net/sec2(zJfeLKS4hcIFUO91WW-ZCIkeOIxUHGs4wtcm3Cp2xkvbqYctIItB4dhQeXTQYOyO2xZivRR_iLwd44Q5ufi2gK5Tsy2yEVKPrO-WB0hpnnoCwmzBDpMSlRGsfGkkQ4LTzFW8SbS0ZMXZMSx0EUYFbA)/video/827/871/538178728_mp4_h264_aac_hd_6.m3u8#cell=cf",
                        "headers": {
                            "User-Agent": "Mozilla/5.0 (X11; Linux x86_64; rv:121.0) Gecko/20100101 Firefox/121.0",
                            "Accept": "*/*"
                        }
                    },
                    {
                        "url": "https://vod.cf.dmcdn.net/sec2(Eh2i3xyjhj0uwwxlAwdHC29_7l5qruZhbDO9ftgE758_WdL2HkVo6GXu-vv7tpa-seEeWOrT0l6qSxNrbVUeiMdI1_Qzi48Q3--kYKyMwJ4T5TOD3eFch4efmnSFbS-bSYlBelyB6Qa038fsUtpb8Q)/video/227/871/538178722_mp4_h264_aac_hd_3.m3u8#cell=cf",
                        "quality": "Dailymotion (Portugués)720p",
                        "videoUrl": "https://vod.cf.dmcdn.net/sec2(Eh2i3xyjhj0uwwxlAwdHC29_7l5qruZhbDO9ftgE758_WdL2HkVo6GXu-vv7tpa-seEeWOrT0l6qSxNrbVUeiMdI1_Qzi48Q3--kYKyMwJ4T5TOD3eFch4efmnSFbS-bSYlBelyB6Qa038fsUtpb8Q)/video/227/871/538178722_mp4_h264_aac_hd_3.m3u8#cell=cf",
                        "headers": {
                            "User-Agent": "Mozilla/5.0 (X11; Linux x86_64; rv:121.0) Gecko/20100101 Firefox/121.0",
                            "Accept": "*/*"
                        }
                    },
                    {
                        "url": "https://vod.cf.dmcdn.net/sec2(hvc3qlT-yFFmIL9vXF_Ef1zfQWukGJKsnWuDbcr9cqqTRxcxT0Cnf7rftCabdYMYVuhKDAM0suQtF4h9TV0x9ifFmuQiRxLa4buamebR7vD6pZl-b1cg0ari0wOGi_bwU_S53YYSu4O6DNT7QzLwmg)/video/027/871/538178720_mp4_h264_aac_hd_8.m3u8#cell=cf",
                        "quality": "Dailymotion (Español)720p",
                        "videoUrl": "https://vod.cf.dmcdn.net/sec2(hvc3qlT-yFFmIL9vXF_Ef1zfQWukGJKsnWuDbcr9cqqTRxcxT0Cnf7rftCabdYMYVuhKDAM0suQtF4h9TV0x9ifFmuQiRxLa4buamebR7vD6pZl-b1cg0ari0wOGi_bwU_S53YYSu4O6DNT7QzLwmg)/video/027/871/538178720_mp4_h264_aac_hd_8.m3u8#cell=cf",
                        "headers": {
                            "User-Agent": "Mozilla/5.0 (X11; Linux x86_64; rv:121.0) Gecko/20100101 Firefox/121.0",
                            "Accept": "*/*"
                        }
                    },
                    {
                        "url": "https://vod.cf.dmcdn.net/sec2(bD_uPaq8Jq_PMykISF2xlPRl3Alw6orx_wFBrGuGv3gciuqy2yPLYUE-o-jTNd1apalTuQBxA9TTwhWIzN5BvYOPYCF6XpqASkWOmQA4u5D6DospELN8i5BHMW2O5PyVcYiYSZ36m4C1PwIPby28yA)/video/427/871/538178724_mp4_h264_aac_hd_8.m3u8#cell=cf",
                        "quality": "Dailymotion (Indonesian)720p",
                        "videoUrl": "https://vod.cf.dmcdn.net/sec2(bD_uPaq8Jq_PMykISF2xlPRl3Alw6orx_wFBrGuGv3gciuqy2yPLYUE-o-jTNd1apalTuQBxA9TTwhWIzN5BvYOPYCF6XpqASkWOmQA4u5D6DospELN8i5BHMW2O5PyVcYiYSZ36m4C1PwIPby28yA)/video/427/871/538178724_mp4_h264_aac_hd_8.m3u8#cell=cf",
                        "headers": {
                            "User-Agent": "Mozilla/5.0 (X11; Linux x86_64; rv:121.0) Gecko/20100101 Firefox/121.0",
                            "Accept": "*/*"
                        }
                    },
                    {
                        "url": "https://a2.mp4upload.com:183/d/xwxrww7zz3b4quuou6quqj2gddf6a4qyxxjsyyt2x2qtl5jihvedt6rfaan7chf6hxd4l2ky/video.mp4",
                        "quality": "(English) - Mp4Upload - 1080p",
                        "videoUrl": "https://a2.mp4upload.com:183/d/xwxrww7zz3b4quuou6quqj2gddf6a4qyxxjsyyt2x2qtl5jihvedt6rfaan7chf6hxd4l2ky/video.mp4",
                        "headers": {
                            "User-Agent": "Mozilla/5.0 (X11; Linux x86_64; rv:121.0) Gecko/20100101 Firefox/121.0",
                            "referer": "https://mp4upload.com/"
                        }
                    },
                    {
                        "url": "https://vod.cf.dmcdn.net/sec2(QUK4j2dJ9fA1GV3vG9ffvtDEc_AYY2oTEnM3NtJ2GnEEnCSr0JjhMvnHTtr-n1ChDKNi7GN4k85LGP0xkTKy4zHav-0OcTbb0rcazxfMkGNjzxNt7v5iysmQSUS56KVFqRx3_DZF-bZw-u4TIyfB_Q)/video/817/871/538178718_mp4_h264_aac_fhd_7.m3u8#cell=cf",
                        "quality": "Dailymotion (English)1080p",
                        "videoUrl": "https://vod.cf.dmcdn.net/sec2(QUK4j2dJ9fA1GV3vG9ffvtDEc_AYY2oTEnM3NtJ2GnEEnCSr0JjhMvnHTtr-n1ChDKNi7GN4k85LGP0xkTKy4zHav-0OcTbb0rcazxfMkGNjzxNt7v5iysmQSUS56KVFqRx3_DZF-bZw-u4TIyfB_Q)/video/817/871/538178718_mp4_h264_aac_fhd_7.m3u8#cell=cf",
                        "headers": {
                            "User-Agent": "Mozilla/5.0 (X11; Linux x86_64; rv:121.0) Gecko/20100101 Firefox/121.0",
                            "Accept": "*/*"
                        }
                    },
                    {
                        "url": "https://vod.cf.dmcdn.net/sec2(gshzpbzJMfPY7J9zoQYEbTVXAdC3eBraaBoxxXEQNowIvQUmGPpK48nRjxnVVg7IaRlpM7JJUsaJxljrByvK0Jnt2W1KPqY-WpoL2TdJV4b6NJeqzAjDDwAYkQrcv2LX-QtT2VpmEvusCtzU1WsHYA)/video/817/871/538178718_mp4_h264_aac_hq_7.m3u8#cell=cf",
                        "quality": "Dailymotion (English)480p",
                        "videoUrl": "https://vod.cf.dmcdn.net/sec2(gshzpbzJMfPY7J9zoQYEbTVXAdC3eBraaBoxxXEQNowIvQUmGPpK48nRjxnVVg7IaRlpM7JJUsaJxljrByvK0Jnt2W1KPqY-WpoL2TdJV4b6NJeqzAjDDwAYkQrcv2LX-QtT2VpmEvusCtzU1WsHYA)/video/817/871/538178718_mp4_h264_aac_hq_7.m3u8#cell=cf",
                        "headers": {
                            "User-Agent": "Mozilla/5.0 (X11; Linux x86_64; rv:121.0) Gecko/20100101 Firefox/121.0",
                            "Accept": "*/*"
                        }
                    },
                    {
                        "url": "https://vod.cf.dmcdn.net/sec2(NOzL_AGifPCBYgAzUYFVv7kYXtDKi5FiO9RJm0kf3nuHLfh2lDdffvbAne6uCV0-2pGGnXn2jloLWH2lgmiA2enjikTW-rvqM9OWBlAzWmcB8PM7Zz8SlsFxLYOOii8ur1ePXJKcmqVKzunVYeXlLg)/video/817/871/538178718_mp4_h264_aac_7.m3u8#cell=cf",
                        "quality": "Dailymotion (English)288p",
                        "videoUrl": "https://vod.cf.dmcdn.net/sec2(NOzL_AGifPCBYgAzUYFVv7kYXtDKi5FiO9RJm0kf3nuHLfh2lDdffvbAne6uCV0-2pGGnXn2jloLWH2lgmiA2enjikTW-rvqM9OWBlAzWmcB8PM7Zz8SlsFxLYOOii8ur1ePXJKcmqVKzunVYeXlLg)/video/817/871/538178718_mp4_h264_aac_7.m3u8#cell=cf",
                        "headers": {
                            "User-Agent": "Mozilla/5.0 (X11; Linux x86_64; rv:121.0) Gecko/20100101 Firefox/121.0",
                            "Accept": "*/*"
                        }
                    },
                    {
                        "url": "https://a2.mp4upload.com:183/d/xwxrqw7zz3b4quuou6qr4okoceifm6zwaegteswno7fd45n3flsbid4osj3ggqguapuxo7gz/video.mp4",
                        "quality": "(العَرَبِيَّة) - Mp4Upload - 1080p",
                        "videoUrl": "https://a2.mp4upload.com:183/d/xwxrqw7zz3b4quuou6qr4okoceifm6zwaegteswno7fd45n3flsbid4osj3ggqguapuxo7gz/video.mp4",
                        "headers": {
                            "User-Agent": "Mozilla/5.0 (X11; Linux x86_64; rv:121.0) Gecko/20100101 Firefox/121.0",
                            "referer": "https://mp4upload.com/"
                        }
                    },
                    {
                        "url": "https://vod.cf.dmcdn.net/sec2(nURk4QykeHGg_rqSogaGazPMWCM9pL9C3Ch-8uQXeADtJclpNEBkb6KN0sequ-afJ0dubxye4mn26DOOoXyvEg9uc8M3DdQH7rX5R-X_5EA9V8ifKgjX0M5ZEnltn9ybcVVTVIR5k0kRAqiPM2vQZA)/video/627/871/538178726_mp4_h264_aac_fhd_8.m3u8#cell=cf",
                        "quality": "Dailymotion (العَرَبِيَّة)1080p",
                        "videoUrl": "https://vod.cf.dmcdn.net/sec2(nURk4QykeHGg_rqSogaGazPMWCM9pL9C3Ch-8uQXeADtJclpNEBkb6KN0sequ-afJ0dubxye4mn26DOOoXyvEg9uc8M3DdQH7rX5R-X_5EA9V8ifKgjX0M5ZEnltn9ybcVVTVIR5k0kRAqiPM2vQZA)/video/627/871/538178726_mp4_h264_aac_fhd_8.m3u8#cell=cf",
                        "headers": {
                            "User-Agent": "Mozilla/5.0 (X11; Linux x86_64; rv:121.0) Gecko/20100101 Firefox/121.0",
                            "Accept": "*/*"
                        }
                    },
                    {
                        "url": "https://vod.cf.dmcdn.net/sec2(smUfIKx3YZRu9dbdN1VFh23qcTWht-EvPND8QAqVTwEZJpbgAgc7y0d8hO-Dn3mGG6qHic6FPZ6LFKDDZXcz0zixBR0xJW6xWkqq7gdSM7aDMKV1LDLXcktVFM1Lpc4CNZwKIOxGEfby_gjRZsnA8w)/video/627/871/538178726_mp4_h264_aac_hq_8.m3u8#cell=cf",
                        "quality": "Dailymotion (العَرَبِيَّة)480p",
                        "videoUrl": "https://vod.cf.dmcdn.net/sec2(smUfIKx3YZRu9dbdN1VFh23qcTWht-EvPND8QAqVTwEZJpbgAgc7y0d8hO-Dn3mGG6qHic6FPZ6LFKDDZXcz0zixBR0xJW6xWkqq7gdSM7aDMKV1LDLXcktVFM1Lpc4CNZwKIOxGEfby_gjRZsnA8w)/video/627/871/538178726_mp4_h264_aac_hq_8.m3u8#cell=cf",
                        "headers": {
                            "User-Agent": "Mozilla/5.0 (X11; Linux x86_64; rv:121.0) Gecko/20100101 Firefox/121.0",
                            "Accept": "*/*"
                        }
                    },
                    {
                        "url": "https://vod.cf.dmcdn.net/sec2(BMubWHfAGUZlQJLMwdcDFEBXPvsFx3HAQu8FUZwYnD8z2ojGM4p5lqKLALkKs8S8c_TmYGj2MAcJlDLvP8ICTR-PimMX6NlA0n4oIxViZsBbWmqnnM1_8JwTiAlpE3xm5cWFQXVWKv1hbvCWxJ_qoA)/video/627/871/538178726_mp4_h264_aac_8.m3u8#cell=cf",
                        "quality": "Dailymotion (العَرَبِيَّة)288p",
                        "videoUrl": "https://vod.cf.dmcdn.net/sec2(BMubWHfAGUZlQJLMwdcDFEBXPvsFx3HAQu8FUZwYnD8z2ojGM4p5lqKLALkKs8S8c_TmYGj2MAcJlDLvP8ICTR-PimMX6NlA0n4oIxViZsBbWmqnnM1_8JwTiAlpE3xm5cWFQXVWKv1hbvCWxJ_qoA)/video/627/871/538178726_mp4_h264_aac_8.m3u8#cell=cf",
                        "headers": {
                            "User-Agent": "Mozilla/5.0 (X11; Linux x86_64; rv:121.0) Gecko/20100101 Firefox/121.0",
                            "Accept": "*/*"
                        }
                    },
                    {
                        "url": "https://a2.mp4upload.com:183/d/xwxr4w7zz3b4quuou6qrqi2ijvq7ct34suvv3vynhr6huzazbpf7zomt6fselscgdbojkzqw/video.mp4",
                        "quality": "(Türkçe) - Mp4Upload - 1080p",
                        "videoUrl": "https://a2.mp4upload.com:183/d/xwxr4w7zz3b4quuou6qrqi2ijvq7ct34suvv3vynhr6huzazbpf7zomt6fselscgdbojkzqw/video.mp4",
                        "headers": {
                            "User-Agent": "Mozilla/5.0 (X11; Linux x86_64; rv:121.0) Gecko/20100101 Firefox/121.0",
                            "referer": "https://mp4upload.com/"
                        }
                    },
                    {
                        "url": "https://vod.cf.dmcdn.net/sec2(g2ZV761EZxQWvOFBaoqh7Wzh27x3IRGYZvojfCHBbMV4VKjXPxa9t1haPem__RAs_FRzWIRgC4xzOpCA8q4iKKeOcMDqnQvVKS0YWyFRKUIZUALdE0Gd3Pv6bRgY3zF6FykyAeoZfilbTCL-PCRFaA)/video/237/871/538178732_mp4_h264_aac_fhd_8.m3u8#cell=cf",
                        "quality": "Dailymotion (Türkçe)1080p",
                        "videoUrl": "https://vod.cf.dmcdn.net/sec2(g2ZV761EZxQWvOFBaoqh7Wzh27x3IRGYZvojfCHBbMV4VKjXPxa9t1haPem__RAs_FRzWIRgC4xzOpCA8q4iKKeOcMDqnQvVKS0YWyFRKUIZUALdE0Gd3Pv6bRgY3zF6FykyAeoZfilbTCL-PCRFaA)/video/237/871/538178732_mp4_h264_aac_fhd_8.m3u8#cell=cf",
                        "headers": {
                            "User-Agent": "Mozilla/5.0 (X11; Linux x86_64; rv:121.0) Gecko/20100101 Firefox/121.0",
                            "Accept": "*/*"
                        }
                    },
                    {
                        "url": "https://vod.cf.dmcdn.net/sec2(cFaYB3nim_WQvAaCXjAugKTlDdx1y3kZSxK8vTULAONTxCWVuA9hzv5aghqGqOs921teFoKbTRBKUa3vTHdW4qf_0GzhWmMy5ed9lQFgg4WoEZ94Orgd4AcRrP9nTFPDsbWoNEq2LBdDZI20ZD1_vQ)/video/237/871/538178732_mp4_h264_aac_hq_8.m3u8#cell=cf",
                        "quality": "Dailymotion (Türkçe)480p",
                        "videoUrl": "https://vod.cf.dmcdn.net/sec2(cFaYB3nim_WQvAaCXjAugKTlDdx1y3kZSxK8vTULAONTxCWVuA9hzv5aghqGqOs921teFoKbTRBKUa3vTHdW4qf_0GzhWmMy5ed9lQFgg4WoEZ94Orgd4AcRrP9nTFPDsbWoNEq2LBdDZI20ZD1_vQ)/video/237/871/538178732_mp4_h264_aac_hq_8.m3u8#cell=cf",
                        "headers": {
                            "User-Agent": "Mozilla/5.0 (X11; Linux x86_64; rv:121.0) Gecko/20100101 Firefox/121.0",
                            "Accept": "*/*"
                        }
                    },
                    {
                        "url": "https://vod.cf.dmcdn.net/sec2(tfQsAp-uwZvNA93-XmUoWF1YSl-UyWJSMoQMUTYVwRna9K60I0M_qGOaf3g8ZD1p8VXcqA1BEWMSJyHEZd6QE8_vx4fdy0_WiCYpBGOhOvYDXuGXfyEeqEAT5qe1rBpoyCeFHfUrWtKUcrweGJgsOg)/video/237/871/538178732_mp4_h264_aac_8.m3u8#cell=cf",
                        "quality": "Dailymotion (Türkçe)288p",
                        "videoUrl": "https://vod.cf.dmcdn.net/sec2(tfQsAp-uwZvNA93-XmUoWF1YSl-UyWJSMoQMUTYVwRna9K60I0M_qGOaf3g8ZD1p8VXcqA1BEWMSJyHEZd6QE8_vx4fdy0_WiCYpBGOhOvYDXuGXfyEeqEAT5qe1rBpoyCeFHfUrWtKUcrweGJgsOg)/video/237/871/538178732_mp4_h264_aac_8.m3u8#cell=cf",
                        "headers": {
                            "User-Agent": "Mozilla/5.0 (X11; Linux x86_64; rv:121.0) Gecko/20100101 Firefox/121.0",
                            "Accept": "*/*"
                        }
                    },
                    {
                        "url": "https://a2.mp4upload.com:183/d/xwxr6w7zz3b4quuou6quqikfc6ax4waxbyix6bqklzkte45owcppayfbwude3mh25u5mchlx/video.mp4",
                        "quality": "(ไทย) - Mp4Upload - 1080p",
                        "videoUrl": "https://a2.mp4upload.com:183/d/xwxr6w7zz3b4quuou6quqikfc6ax4waxbyix6bqklzkte45owcppayfbwude3mh25u5mchlx/video.mp4",
                        "headers": {
                            "User-Agent": "Mozilla/5.0 (X11; Linux x86_64; rv:121.0) Gecko/20100101 Firefox/121.0",
                            "referer": "https://mp4upload.com/"
                        }
                    },
                    {
                        "url": "https://vod.cf.dmcdn.net/sec2(UnluTAE6STADs6jA0pcisGrGatEQ5DFU3mrMe0hZpoqSfhOf4fbY-ZMNF4m3ljNxkdY64HdtpbpddVoiKL_oLggZkKMj5ky3FYAKIXBf2NVPkluCx9afxG5refRZ7350mwXb6SWIwHWG45H6FnoVig)/video/827/871/538178728_mp4_h264_aac_fhd_6.m3u8#cell=cf",
                        "quality": "Dailymotion (ไทย)1080p",
                        "videoUrl": "https://vod.cf.dmcdn.net/sec2(UnluTAE6STADs6jA0pcisGrGatEQ5DFU3mrMe0hZpoqSfhOf4fbY-ZMNF4m3ljNxkdY64HdtpbpddVoiKL_oLggZkKMj5ky3FYAKIXBf2NVPkluCx9afxG5refRZ7350mwXb6SWIwHWG45H6FnoVig)/video/827/871/538178728_mp4_h264_aac_fhd_6.m3u8#cell=cf",
                        "headers": {
                            "User-Agent": "Mozilla/5.0 (X11; Linux x86_64; rv:121.0) Gecko/20100101 Firefox/121.0",
                            "Accept": "*/*"
                        }
                    },
                    {
                        "url": "https://vod.cf.dmcdn.net/sec2(AGcPvkWO3MKGrP-Ai1503GbuJO5l48XfJpUVkjzR5EGFEVd6eS5Dqc4vKXNyYRZWrOs5_oBe_mWik6lqgvJsdbLSh7MsBK3rG8f3-ZXwm4Rf8tYgYji3Vbb9eWAY7FwSXEKD8flL1OJYYjShN1uUyQ)/video/827/871/538178728_mp4_h264_aac_hq_6.m3u8#cell=cf",
                        "quality": "Dailymotion (ไทย)480p",
                        "videoUrl": "https://vod.cf.dmcdn.net/sec2(AGcPvkWO3MKGrP-Ai1503GbuJO5l48XfJpUVkjzR5EGFEVd6eS5Dqc4vKXNyYRZWrOs5_oBe_mWik6lqgvJsdbLSh7MsBK3rG8f3-ZXwm4Rf8tYgYji3Vbb9eWAY7FwSXEKD8flL1OJYYjShN1uUyQ)/video/827/871/538178728_mp4_h264_aac_hq_6.m3u8#cell=cf",
                        "headers": {
                            "User-Agent": "Mozilla/5.0 (X11; Linux x86_64; rv:121.0) Gecko/20100101 Firefox/121.0",
                            "Accept": "*/*"
                        }
                    },
                    {
                        "url": "https://vod.cf.dmcdn.net/sec2(ga1j7q3tND38qwRdTvb_ZLInb_UFpm4f3sil_UmY50OWI4ZD9FCNHwfbAV8bXLzvRmBRgiZmgk57JXlnTYYRC7jSzIaHlJetfFG1PTsfC29sCbnyv6tq__PTO7tUIlK6lyFyMX0ss7dX2K0zS3v7wQ)/video/827/871/538178728_mp4_h264_aac_6.m3u8#cell=cf",
                        "quality": "Dailymotion (ไทย)288p",
                        "videoUrl": "https://vod.cf.dmcdn.net/sec2(ga1j7q3tND38qwRdTvb_ZLInb_UFpm4f3sil_UmY50OWI4ZD9FCNHwfbAV8bXLzvRmBRgiZmgk57JXlnTYYRC7jSzIaHlJetfFG1PTsfC29sCbnyv6tq__PTO7tUIlK6lyFyMX0ss7dX2K0zS3v7wQ)/video/827/871/538178728_mp4_h264_aac_6.m3u8#cell=cf",
                        "headers": {
                            "User-Agent": "Mozilla/5.0 (X11; Linux x86_64; rv:121.0) Gecko/20100101 Firefox/121.0",
                            "Accept": "*/*"
                        }
                    },
                    {
                        "url": "https://a2.mp4upload.com:183/d/xwxryw7zz3b4quuou6qrgos2c5zlknnxylm2p3xnkk4mnyoax4jwqjsag5abmj5zl7uscmmc/video.mp4",
                        "quality": "(Portugués) - Mp4Upload - 1080p",
                        "videoUrl": "https://a2.mp4upload.com:183/d/xwxryw7zz3b4quuou6qrgos2c5zlknnxylm2p3xnkk4mnyoax4jwqjsag5abmj5zl7uscmmc/video.mp4",
                        "headers": {
                            "User-Agent": "Mozilla/5.0 (X11; Linux x86_64; rv:121.0) Gecko/20100101 Firefox/121.0",
                            "referer": "https://mp4upload.com/"
                        }
                    },
                    {
                        "url": "https://vod.cf.dmcdn.net/sec2(8TK32SH_8UDkIbLGZ5miDuvtP_OjecKa3ibOCRjte12nVVEPTbRiL0LpD5s6L711IbcLgsC6eW5wjBBZTRgeWy7Kh0Y8Kx_UN4wtqkYMqA6pbZj1XHFCGrlDILWZmHDHj_i7Z2J_W3mUFjfdxkhhCg)/video/227/871/538178722_mp4_h264_aac_fhd_3.m3u8#cell=cf",
                        "quality": "Dailymotion (Portugués)1080p",
                        "videoUrl": "https://vod.cf.dmcdn.net/sec2(8TK32SH_8UDkIbLGZ5miDuvtP_OjecKa3ibOCRjte12nVVEPTbRiL0LpD5s6L711IbcLgsC6eW5wjBBZTRgeWy7Kh0Y8Kx_UN4wtqkYMqA6pbZj1XHFCGrlDILWZmHDHj_i7Z2J_W3mUFjfdxkhhCg)/video/227/871/538178722_mp4_h264_aac_fhd_3.m3u8#cell=cf",
                        "headers": {
                            "User-Agent": "Mozilla/5.0 (X11; Linux x86_64; rv:121.0) Gecko/20100101 Firefox/121.0",
                            "Accept": "*/*"
                        }
                    },
                    {
                        "url": "https://vod.cf.dmcdn.net/sec2(yU2gxNHSDeYHinJmPLDk3m2qpLEFuwkNPv36Fz4jQPRUKByVR4_cUFbwFhIOuT1CqVYmPsDZjYPAs_l55q9aIAVB1n1TAsF5xIKsIXeEt7JN_mnl4jqCODAAUUjdkFGQCXCMEb4CgHHF-BDYgXyM_w)/video/227/871/538178722_mp4_h264_aac_hq_3.m3u8#cell=cf",
                        "quality": "Dailymotion (Portugués)480p",
                        "videoUrl": "https://vod.cf.dmcdn.net/sec2(yU2gxNHSDeYHinJmPLDk3m2qpLEFuwkNPv36Fz4jQPRUKByVR4_cUFbwFhIOuT1CqVYmPsDZjYPAs_l55q9aIAVB1n1TAsF5xIKsIXeEt7JN_mnl4jqCODAAUUjdkFGQCXCMEb4CgHHF-BDYgXyM_w)/video/227/871/538178722_mp4_h264_aac_hq_3.m3u8#cell=cf",
                        "headers": {
                            "User-Agent": "Mozilla/5.0 (X11; Linux x86_64; rv:121.0) Gecko/20100101 Firefox/121.0",
                            "Accept": "*/*"
                        }
                    },
                    {
                        "url": "https://vod.cf.dmcdn.net/sec2(fdd7okq-SqtkORBKjA1x1I9XVlfIBNTXny0ZmpL9Wf88y89wK8ZbtLjsiCUJPFVOhnzLf3D-zCHq5IFhzktMr4WFHMaJAjAzDdFhHtkFpYdyqqt7S-IMIGCZNjApyPp7Wnn5PVJ1fTru6qEBfoO9kQ)/video/227/871/538178722_mp4_h264_aac_3.m3u8#cell=cf",
                        "quality": "Dailymotion (Portugués)288p",
                        "videoUrl": "https://vod.cf.dmcdn.net/sec2(fdd7okq-SqtkORBKjA1x1I9XVlfIBNTXny0ZmpL9Wf88y89wK8ZbtLjsiCUJPFVOhnzLf3D-zCHq5IFhzktMr4WFHMaJAjAzDdFhHtkFpYdyqqt7S-IMIGCZNjApyPp7Wnn5PVJ1fTru6qEBfoO9kQ)/video/227/871/538178722_mp4_h264_aac_3.m3u8#cell=cf",
                        "headers": {
                            "User-Agent": "Mozilla/5.0 (X11; Linux x86_64; rv:121.0) Gecko/20100101 Firefox/121.0",
                            "Accept": "*/*"
                        }
                    },
                    {
                        "url": "https://a2.mp4upload.com:183/d/xwxruw7zz3b4quuou6qr222hjg623g3a7veazvcifihsfwnsjjt4xthoqixtxctzpswnto6q/video.mp4",
                        "quality": "(Español) - Mp4Upload - 1080p",
                        "videoUrl": "https://a2.mp4upload.com:183/d/xwxruw7zz3b4quuou6qr222hjg623g3a7veazvcifihsfwnsjjt4xthoqixtxctzpswnto6q/video.mp4",
                        "headers": {
                            "User-Agent": "Mozilla/5.0 (X11; Linux x86_64; rv:121.0) Gecko/20100101 Firefox/121.0",
                            "referer": "https://mp4upload.com/"
                        }
                    },
                    {
                        "url": "https://vod.cf.dmcdn.net/sec2(02oCzb_G-ur40mZs8EIfgIUWfrPvKTFkjE9XxkiWEVrF98vplFB3R6dYYCwfARrG2ZDqwW_LA4e4eCsksS6LDSp90iCgJshQOHTINLPqE2ypcOZEf34CPFIf3XAhLef_5Zyod0kGLcqTIMnksKZGYg)/video/027/871/538178720_mp4_h264_aac_fhd_8.m3u8#cell=cf",
                        "quality": "Dailymotion (Español)1080p",
                        "videoUrl": "https://vod.cf.dmcdn.net/sec2(02oCzb_G-ur40mZs8EIfgIUWfrPvKTFkjE9XxkiWEVrF98vplFB3R6dYYCwfARrG2ZDqwW_LA4e4eCsksS6LDSp90iCgJshQOHTINLPqE2ypcOZEf34CPFIf3XAhLef_5Zyod0kGLcqTIMnksKZGYg)/video/027/871/538178720_mp4_h264_aac_fhd_8.m3u8#cell=cf",
                        "headers": {
                            "User-Agent": "Mozilla/5.0 (X11; Linux x86_64; rv:121.0) Gecko/20100101 Firefox/121.0",
                            "Accept": "*/*"
                        }
                    },
                    {
                        "url": "https://vod.cf.dmcdn.net/sec2(IS4Hnx79DK7X8ptY037R1MvMVZXvm8TRUYeYwU_G9ueXpfpxThcQ5Mo8gdqptdtq7utMXd9-kHFyH7nAJGzVZczdPOiRpYEcsM9Jete1CHbHQW-CzI3gJh1dhKofre6VfidzdpTsEHPJVY5v_1fwEA)/video/027/871/538178720_mp4_h264_aac_hq_8.m3u8#cell=cf",
                        "quality": "Dailymotion (Español)480p",
                        "videoUrl": "https://vod.cf.dmcdn.net/sec2(IS4Hnx79DK7X8ptY037R1MvMVZXvm8TRUYeYwU_G9ueXpfpxThcQ5Mo8gdqptdtq7utMXd9-kHFyH7nAJGzVZczdPOiRpYEcsM9Jete1CHbHQW-CzI3gJh1dhKofre6VfidzdpTsEHPJVY5v_1fwEA)/video/027/871/538178720_mp4_h264_aac_hq_8.m3u8#cell=cf",
                        "headers": {
                            "User-Agent": "Mozilla/5.0 (X11; Linux x86_64; rv:121.0) Gecko/20100101 Firefox/121.0",
                            "Accept": "*/*"
                        }
                    },
                    {
                        "url": "https://vod.cf.dmcdn.net/sec2(RXk2sDDJVF8v2J7VtvWmaQFdQLHFvpNfUjbSsictfFdEf7qYzEsRMpV7Is9MI91lcKyEjG_axAd6waEtnjf52pFtHmJx2a4uhoREN8iPjbz-z_GPlRJ6AS6FWW3Ji6Y78EovguCOvNnJrY1LkAxVTA)/video/027/871/538178720_mp4_h264_aac_8.m3u8#cell=cf",
                        "quality": "Dailymotion (Español)288p",
                        "videoUrl": "https://vod.cf.dmcdn.net/sec2(RXk2sDDJVF8v2J7VtvWmaQFdQLHFvpNfUjbSsictfFdEf7qYzEsRMpV7Is9MI91lcKyEjG_axAd6waEtnjf52pFtHmJx2a4uhoREN8iPjbz-z_GPlRJ6AS6FWW3Ji6Y78EovguCOvNnJrY1LkAxVTA)/video/027/871/538178720_mp4_h264_aac_8.m3u8#cell=cf",
                        "headers": {
                            "User-Agent": "Mozilla/5.0 (X11; Linux x86_64; rv:121.0) Gecko/20100101 Firefox/121.0",
                            "Accept": "*/*"
                        }
                    },
                    {
                        "url": "https://a2.mp4upload.com:183/d/xwxr2w7zz3b4quuou6qrsncwkvzodfrq2p53qmsn2aoggoiiixlokxtsnj45q2ufyfrbhc75/video.mp4",
                        "quality": "(Indonesian) - Mp4Upload - 1080p",
                        "videoUrl": "https://a2.mp4upload.com:183/d/xwxr2w7zz3b4quuou6qrsncwkvzodfrq2p53qmsn2aoggoiiixlokxtsnj45q2ufyfrbhc75/video.mp4",
                        "headers": {
                            "User-Agent": "Mozilla/5.0 (X11; Linux x86_64; rv:121.0) Gecko/20100101 Firefox/121.0",
                            "referer": "https://mp4upload.com/"
                        }
                    },
                    {
                        "url": "https://vod.cf.dmcdn.net/sec2(9sRuSnee1IUcQfoRg6khMAj2hLEyycI6_T7erjya7-XgbjsDDXq8W3PR_JOl6evmYZJZ-MyzLq7G2VJ24B-n-vqYZ1oxt_f9Ha5i87qhHQK3_trNZitk79NQiQ2GXY8S2jX6YNMIyK5vIYI3qb6rNA)/video/427/871/538178724_mp4_h264_aac_fhd_8.m3u8#cell=cf",
                        "quality": "Dailymotion (Indonesian)1080p",
                        "videoUrl": "https://vod.cf.dmcdn.net/sec2(9sRuSnee1IUcQfoRg6khMAj2hLEyycI6_T7erjya7-XgbjsDDXq8W3PR_JOl6evmYZJZ-MyzLq7G2VJ24B-n-vqYZ1oxt_f9Ha5i87qhHQK3_trNZitk79NQiQ2GXY8S2jX6YNMIyK5vIYI3qb6rNA)/video/427/871/538178724_mp4_h264_aac_fhd_8.m3u8#cell=cf",
                        "headers": {
                            "User-Agent": "Mozilla/5.0 (X11; Linux x86_64; rv:121.0) Gecko/20100101 Firefox/121.0",
                            "Accept": "*/*"
                        }
                    },
                    {
                        "url": "https://vod.cf.dmcdn.net/sec2(5zgoYsXJIauOTZV7c9WMlO82iBFvIP9aNEKv88_ek6i2boRGfnivjVE-Hees_zikC4P46bwfSjncP2sGwolBJaWRIHXtir46O33au4qbQRTaZGwoA_A3Mc32bj25Xww8T8UPbXLy3Y0m9uKNoM2VTg)/video/427/871/538178724_mp4_h264_aac_hq_8.m3u8#cell=cf",
                        "quality": "Dailymotion (Indonesian)480p",
                        "videoUrl": "https://vod.cf.dmcdn.net/sec2(5zgoYsXJIauOTZV7c9WMlO82iBFvIP9aNEKv88_ek6i2boRGfnivjVE-Hees_zikC4P46bwfSjncP2sGwolBJaWRIHXtir46O33au4qbQRTaZGwoA_A3Mc32bj25Xww8T8UPbXLy3Y0m9uKNoM2VTg)/video/427/871/538178724_mp4_h264_aac_hq_8.m3u8#cell=cf",
                        "headers": {
                            "User-Agent": "Mozilla/5.0 (X11; Linux x86_64; rv:121.0) Gecko/20100101 Firefox/121.0",
                            "Accept": "*/*"
                        }
                    },
                    {
                        "url": "https://vod.cf.dmcdn.net/sec2(EW589lxPfgvteISD5Khr1ejwW96rukO8-5sVEJ0dkLbZuWwmCVGglG186L8MUveDZRy6SZIAU9xZpiD0PNwaQQ6DfarTiV5kOWNzq0eoWkOWz95oEUI6bKTclvs6FGchAo8ZGyoqOlHM9OGHgtickg)/video/427/871/538178724_mp4_h264_aac_8.m3u8#cell=cf",
                        "quality": "Dailymotion (Indonesian)288p",
                        "videoUrl": "https://vod.cf.dmcdn.net/sec2(EW589lxPfgvteISD5Khr1ejwW96rukO8-5sVEJ0dkLbZuWwmCVGglG186L8MUveDZRy6SZIAU9xZpiD0PNwaQQ6DfarTiV5kOWNzq0eoWkOWz95oEUI6bKTclvs6FGchAo8ZGyoqOlHM9OGHgtickg)/video/427/871/538178724_mp4_h264_aac_8.m3u8#cell=cf",
                        "headers": {
                            "User-Agent": "Mozilla/5.0 (X11; Linux x86_64; rv:121.0) Gecko/20100101 Firefox/121.0",
                            "Accept": "*/*"
                        }
                    }
                ],
                "passed": true
            }
        }
    }
]