[
    {
        "name": "Egy Dead (AR)",
        "results": {
            "popular": {
                "error": "eu.kanade.tachiyomi.network.HttpException: HTTP error 403",
                "passed": false
            },
            "latest": {
                "result": [
                    {
                        "animes": [
                            {
                                "url": "/episode/مسلسل-the-rookie-الموسم-السادس-الحلقة-5-مترجمة/",
                                "title": "مسلسل The Rookie الموسم السادس الحلقة 5 مترجمة",
                                "thumbnail_url": "https://egydead.space/wp-content/uploads/2024/02/مسلسل-The-Rookie-الموسم-السادس-210x280.jpg"
                            },
                            {
                                "url": "/episode/مسلسل-fbi-international-الموسم-الثالث-الحلقة-7-مترجمة/",
                                "title": "مسلسل FBI International الموسم الثالث الحلقة 7 مترجمة",
                                "thumbnail_url": "https://egydead.space/wp-content/uploads/2024/02/مسلسل-FBI-International-الموسم-الثالث-230x280.jpeg"
                            },
                            {
                                "url": "/episode/مسلسل-السلطان-محمد-الفاتح-الحلقة-6-مترج/",
                                "title": "مسلسل السلطان محمد الفاتح الحلقة 6 مترجمة",
                                "thumbnail_url": "https://egydead.space/wp-content/uploads/2024/03/مسلسل-السلطان-محمد-الفاتح-2024-مترجم-225x280.jpg"
                            },
                            {
                                "url": "/episode/مسلسل-التركي-العقدة-الحلقة-8-مدبلجة/",
                                "title": "مسلسل التركي العقدة الحلقة 8 مدبلجة",
                                "thumbnail_url": "https://egydead.space/wp-content/uploads/2024/02/مسلسل-Dugum-2024-مترجم-كامل-210x280.jpg"
                            },
                            {
                                "url": "/episode/مسلسل-will-trent-الموسم-الثاني-الحلقة-5-مترجمة/",
                                "title": "مسلسل Will Trent الموسم الثاني الحلقة 5 مترجمة",
                                "thumbnail_url": "https://egydead.space/wp-content/uploads/2024/02/مسلسل-Will-Trent-الموسم-الثاني-210x280.jpg"
                            },
                            {
                                "url": "/episode/مسلسل-the-bad-batch-الموسم-الثالث-الحلقة-11-مترجمة/",
                                "title": "مسلسل The Bad Batch الموسم الثالث الحلقة 11 مترجمة",
                                "thumbnail_url": "https://egydead.space/wp-content/uploads/2024/02/مسلسل-The-Bad-Batch-الموسم-الثالث-203x280.jpg"
                            },
                            {
                                "url": "/episode/مسلسل-the-bad-batch-الموسم-الثالث-الحلقة-10-مترجمة/",
                                "title": "مسلسل The Bad Batch الموسم الثالث الحلقة 10 مترجمة",
                                "thumbnail_url": "https://egydead.space/wp-content/uploads/2024/02/مسلسل-The-Bad-Batch-الموسم-الثالث-203x280.jpg"
                            },
                            {
                                "url": "/episode/مسلسل-the-good-doctor-الموسم-السابع-الحلقة-5-مترجمة/",
                                "title": "مسلسل The Good Doctor الموسم السابع الحلقة 5 مترجمة",
                                "thumbnail_url": "https://egydead.space/wp-content/uploads/2024/02/مسلسل-The-Good-Doctor-الموسم-السابع-225x280.jpg"
                            },
                            {
                                "url": "/episode/مسلسل-fbi-الموسم-السادس-الحلقة-7-مترجمة/",
                                "title": "مسلسل FBI الموسم السادس الحلقة 7 مترجمة",
                                "thumbnail_url": "https://egydead.space/wp-content/uploads/2024/02/مسلسل-FBI-الموسم-السادس-195x280.jpg"
                            },
                            {
                                "url": "/episode/مسلسل-fbi-most-wanted-الموسم-الخامس-الحلقة-7-مترجمة/",
                                "title": "مسلسل FBI Most Wanted الموسم الخامس الحلقة 7 مترجمة",
                                "thumbnail_url": "https://egydead.space/wp-content/uploads/2024/02/مسلسل-FBI-Most-Wanted-الموسم-الخامس-203x280.jpg"
                            },
                            {
                                "url": "/assembly/سلسلة-افلام-skyline-مترجمة-كاملة/",
                                "title": "سلسلة افلام Skyline مترجمة كاملة",
                                "thumbnail_url": "https://egydead.space/wp-content/uploads/2024/04/سلسلة-افلام-Skyline-مترجمة-كاملة-217x280.jpg"
                            },
                            {
                                "url": "/مشاهدة-فيلم-skylines-3-2020-مترجم/",
                                "title": "مشاهدة فيلم Skylines 3 2020 مترجم",
                                "thumbnail_url": "https://egydead.space/wp-content/uploads/2021/01/فيلم-Skylines-2020-مترجم-1-225x280.jpg"
                            },
                            {
                                "url": "/مشاهدة-فيلم-beyond-skyline-2-2017-مترجم/",
                                "title": "مشاهدة فيلم Beyond Skyline 2 2017 مترجم",
                                "thumbnail_url": "https://egydead.space/wp-content/uploads/2018/08/فيلم-Beyond-Skyline-2-2017-مترجم-217x280.jpg"
                            },
                            {
                                "url": "/مشاهدة-فيلم-skyline-2010-مترجم/",
                                "title": "مشاهدة فيلم Skyline 1 2010 مترجم",
                                "thumbnail_url": "https://egydead.space/wp-content/uploads/2018/08/فيلم-Skyline-1-2010-مترجم-217x280.jpg"
                            },
                            {
                                "url": "/episode/مسلسل-the-cleaning-lady-الموسم-الثالث-الحلقة-5-مترجمة/",
                                "title": "مسلسل The Cleaning Lady الموسم الثالث الحلقة 5 مترجمة",
                                "thumbnail_url": "https://egydead.space/wp-content/uploads/2024/03/مسلسل-The-Cleaning-Lady-الموسم-الثالث-210x280.jpg"
                            },
                            {
                                "url": "/episode/مسلسل-alert-الموسم-الثاني-الحلقة-5-مترجمة/",
                                "title": "مسلسل Alert الموسم الثاني الحلقة 5 مترجمة",
                                "thumbnail_url": "https://egydead.space/wp-content/uploads/2024/03/مسلسل-Alert-الموسم-الثاني-225x280.jpg"
                            },
                            {
                                "url": "/مشاهدة-فيلم-resident-evil-degeneration-2008-مترجم/",
                                "title": "مشاهدة فيلم Resident Evil Degeneration 2008 مترجم",
                                "thumbnail_url": "https://egydead.space/wp-content/uploads/2020/01/فيلم-Resident-Evil-Degeneration-2008-مترجم-217x280.jpg"
                            },
                            {
                                "url": "/مشاهدة-فيلم-spectral-2016-مترجم/",
                                "title": "مشاهدة فيلم Spectral 2016 مترجم",
                                "thumbnail_url": "https://egydead.space/wp-content/uploads/2019/04/فيلم-Spectral-2016-مترجم-225x280.jpg"
                            },
                            {
                                "url": "/مشاهدة-فيلم-zeros-and-ones-2021-مترجم/",
                                "title": "مشاهدة فيلم Zeros and Ones 2021 مترجم",
                                "thumbnail_url": "https://egydead.space/wp-content/uploads/2022/12/فيلم-Zeros-and-Ones-2021-مترجم-217x280.jpg"
                            },
                            {
                                "url": "/مشاهدة-فيلم-scarygirl-2023-مترجم/",
                                "title": "مشاهدة فيلم Scarygirl 2023 مترجم",
                                "thumbnail_url": "https://egydead.space/wp-content/uploads/2023/10/فيلم-Scarygirl-2023-مترجم-197x280.jpg"
                            },
                            {
                                "url": "/فيلم-im-thinking-of-ending-things-2020-مترجم/",
                                "title": "مشاهدة فيلم I’m Thinking of Ending Things 2020 مترجم",
                                "thumbnail_url": "https://egydead.space/wp-content/uploads/2020/09/فيلم-Im-Thinking-of-Ending-Things-2020-مترجم-1-225x280.jpg"
                            },
                            {
                                "url": "/مشاهدة-فيلم-forgotten-experiment-2023-مترجم/",
                                "title": "مشاهدة فيلم Forgotten Experiment 2023 مترجم",
                                "thumbnail_url": "https://egydead.space/wp-content/uploads/2023/10/Forgotten-Experiment-2023-208x280.jpg"
                            },
                            {
                                "url": "/episode/مسلسل-a-gentleman-in-moscow-الحلقة-1-مترجمة/",
                                "title": "مسلسل A Gentleman in Moscow الحلقة 1 مترجمة",
                                "thumbnail_url": "https://egydead.space/wp-content/uploads/2024/04/مسلسل-A-Gentleman-in-Moscow-2024-مترجم-210x280.jpg"
                            },
                            {
                                "url": "/season/مسلسل-a-gentleman-in-moscow-2024-مترجم-كامل/",
                                "title": "مسلسل A Gentleman in Moscow 2024 مترجم كامل",
                                "thumbnail_url": "https://egydead.space/wp-content/uploads/2024/04/مسلسل-A-Gentleman-in-Moscow-2024-مترجم-كامل-187x280.jpg"
                            },
                            {
                                "url": "/episode/مسلسل-the-way-home-الموسم-الثاني-الحلقة-10-مترجمة/",
                                "title": "مسلسل The Way Home الموسم الثاني الحلقة 10 مترجمة",
                                "thumbnail_url": "https://egydead.space/wp-content/uploads/2024/01/مسلسل-The-Way-Home-الموسم-الثاني-210x280.jpg"
                            },
                            {
                                "url": "/episode/مسلسل-ncis-hawaii-الموسم-الثالث-الحلقة-6-مترجمة/",
                                "title": "مسلسل NCIS Hawaii الموسم الثالث الحلقة 6 مترجمة",
                                "thumbnail_url": "https://egydead.space/wp-content/uploads/2024/02/مسلسل-NCIS-Hawaii-الموسم-الثالث-210x280.jpg"
                            },
                            {
                                "url": "/episode/مسلسل-the-neighborhood-الموسم-السادس-الحلقة-6-مترجمة/",
                                "title": "مسلسل The Neighborhood الموسم السادس الحلقة 6 مترجمة",
                                "thumbnail_url": "https://egydead.space/wp-content/uploads/2024/02/مسلسل-The-Neighborhood-الموسم-السادس-225x280.jpg"
                            },
                            {
                                "url": "/episode/مسلسل-bob-hearts-abishola-الموسم-الخامس-الحلقة-9-مترجمة/",
                                "title": "مسلسل Bob Hearts Abishola الموسم الخامس الحلقة 9 مترجمة",
                                "thumbnail_url": "https://egydead.space/wp-content/uploads/2024/02/مسلسل-Bob-Hearts-Abishola-الموسم-الخامس-225x280.jpg"
                            },
                            {
                                "url": "/episode/مسلسل-all-american-الموسم-السادس-الحلقة-1-مترجمة/",
                                "title": "مسلسل All American الموسم السادس الحلقة 1 مترجمة",
                                "thumbnail_url": "https://egydead.space/wp-content/uploads/2024/04/مسلسل-All-American-الموسم-السادس-210x280.jpg"
                            },
                            {
                                "url": "/season/مسلسل-all-american-الموسم-السادس-مترجم-كامل/",
                                "title": "مسلسل All American الموسم السادس مترجم كامل",
                                "thumbnail_url": "https://egydead.space/wp-content/uploads/2024/04/مسلسل-All-American-الموسم-السادس-210x280.jpg"
                            },
                            {
                                "url": "/مشاهدة-فيلم-kiss-kiss-bang-bang-2005-مترجم/",
                                "title": "مشاهدة فيلم Kiss Kiss Bang Bang 2005 مترجم",
                                "thumbnail_url": "https://egydead.space/wp-content/uploads/2022/12/فيلم-Kiss-Kiss-Bang-Bang-2005-مترجم-210x280.jpg"
                            },
                            {
                                "url": "/episode/مسلسل-loot-الموسم-الثاني-الحلقة-2-مترجمة/",
                                "title": "مسلسل Loot الموسم الثاني الحلقة 2 مترجمة",
                                "thumbnail_url": "https://egydead.space/wp-content/uploads/2022/06/مسلسل-Loot-الموسم-الثاني-225x280.jpg"
                            },
                            {
                                "url": "/episode/مسلسل-loot-الموسم-الثاني-الحلقة-1-مترجمة/",
                                "title": "مسلسل Loot الموسم الثاني الحلقة 1 مترجمة",
                                "thumbnail_url": "https://egydead.space/wp-content/uploads/2022/06/مسلسل-Loot-الموسم-الثاني-225x280.jpg"
                            },
                            {
                                "url": "/season/مسلسل-loot-الموسم-الثاني-مترجم-كامل/",
                                "title": "مسلسل Loot الموسم الثاني مترجم كامل",
                                "thumbnail_url": "https://egydead.space/wp-content/uploads/2022/06/مسلسل-Loot-الموسم-الثاني-كامل-225x280.jpg"
                            },
                            {
                                "url": "/serie/مسلسل-loot-2022-مترجم-كامل/",
                                "title": "جميع مواسم مسلسل Loot 2022 مترجم كامل",
                                "thumbnail_url": "https://egydead.space/wp-content/uploads/2022/06/مسلسل-Loot-2022-مترجم-كامل-210x280.jpg"
                            },
                            {
                                "url": "/season/مسلسل-loot-الموسم-الاول-مترجم-كامل/",
                                "title": "مسلسل Loot الموسم الاول مترجم كامل",
                                "thumbnail_url": "https://egydead.space/wp-content/uploads/2022/06/مسلسل-Loot-الموسم-الاول-كامل-207x280.jpg"
                            },
                            {
                                "url": "/فيلم-murder-mystery-2-2023-مترجم/",
                                "title": "مشاهدة فيلم Murder Mystery 2 2023 مترجم",
                                "thumbnail_url": "https://egydead.space/wp-content/uploads/2023/03/Murder-Mystery-2-2023-187x280.jpg"
                            },
                            {
                                "url": "/مشاهدة-فيلم-murder-mystery-2019-مترجم/",
                                "title": "مشاهدة فيلم Murder Mystery 1 2019 مترجم",
                                "thumbnail_url": "https://egydead.space/wp-content/uploads/2019/07/فيلم-Murder-Mystery-2019-مترجم-217x280.jpg"
                            },
                            {
                                "url": "/episode/مسلسل-palm-royale-الحلقة-5-مترجمة/",
                                "title": "مسلسل Palm Royale الحلقة 5 مترجمة",
                                "thumbnail_url": "https://egydead.space/wp-content/uploads/2024/03/مسلسل-Palm-Royale-2024-مترجم-194x280.jpg"
                            },
                            {
                                "url": "/episode/صلاح-الدين-الايوبي-الجزء-الاول-الحلقة-24/",
                                "title": "صلاح الدين الايوبي الجزء الاول الحلقة 24 مدبلجة",
                                "thumbnail_url": "https://egydead.space/wp-content/uploads/2024/03/صلاح-الدين-الايوبي-الجزء-الاول-225x280.jpg"
                            },
                            {
                                "url": "/episode/برنامج-physical-100-الموسم-الثاني-الحلقة-9-مترجمة/",
                                "title": "برنامج Physical 100 الموسم الثاني الحلقة 9 مترجمة",
                                "thumbnail_url": "https://egydead.space/wp-content/uploads/2024/03/برنامج-Physical-100-الموسم-الثاني-225x280.jpg"
                            },
                            {
                                "url": "/episode/برنامج-physical-100-الموسم-الثاني-الحلقة-8-مترجمة/",
                                "title": "برنامج Physical 100 الموسم الثاني الحلقة 8 مترجمة",
                                "thumbnail_url": "https://egydead.space/wp-content/uploads/2024/03/برنامج-Physical-100-الموسم-الثاني-225x280.jpg"
                            },
                            {
                                "url": "/episode/مسلسل-the-new-look-الموسم-الاول-الحلقة-10-مترجمة/",
                                "title": "مسلسل The New Look الموسم الاول الحلقة 10 مترجمة",
                                "thumbnail_url": "https://egydead.space/wp-content/uploads/2024/02/مسلسل-The-New-Look-الموسم-الاول-210x280.jpg"
                            },
                            {
                                "url": "/episode/انمي-shaman-king-flowers-الحلقة-13-مترجمة/",
                                "title": "انمي Shaman King Flowers الحلقة 13 مترجمة",
                                "thumbnail_url": "https://egydead.space/wp-content/uploads/2024/01/انمي-Shaman-King-Flowers-2024-مترجم-225x280.jpg"
                            },
                            {
                                "url": "/episode/برنامج-الدحيح-4-الحلقة-51-ماركو-بولو/",
                                "title": "برنامج الدحيح 4 الحلقة 51 ماركو بولو",
                                "thumbnail_url": "https://egydead.space/wp-content/uploads/2023/09/برنامج-الدحيح-4-كامل-203x280.jpg"
                            },
                            {
                                "url": "/episode/مسلسل-صلاح-الدين-الايوبي-الحلقة-19-مترجم/",
                                "title": "مسلسل صلاح الدين الايوبي الحلقة 19 مترجمة",
                                "thumbnail_url": "https://egydead.space/wp-content/uploads/2023/11/مسلسل-صلاح-الدين-الايوبي-2023-مترجم-225x280.jpg"
                            },
                            {
                                "url": "/فيلم-the-family-plan-مترجم/",
                                "title": "مشاهدة فيلم The Family Plan 2023 مترجم",
                                "thumbnail_url": "https://egydead.space/wp-content/uploads/2023/12/فيلم-The-Family-Plan-2023-مترجم-210x280.jpg"
                            },
                            {
                                "url": "/فيلم-غودزيلا-ضد-كونغ-2-2024-مدبلج/",
                                "title": "فيلم غودزيلا ضد كونغ 2 2024 مدبلج",
                                "thumbnail_url": "https://egydead.space/wp-content/uploads/2024/04/فيلم-غودزيلا-ضد-كونغ-2-2024-مدبلج-225x280.jpg"
                            }
                        ],
                        "hasNextPage": true
                    }
                ],
                "passed": true
            },
            "search": {
                "result": [
                    {
                        "animes": [
                            {
                                "url": "/episode/مسلسل-messis-world-cup-the-rise-of-a-legend-الحلقة-4-مترجمة/",
                                "title": "مسلسل Messi’s World Cup The Rise of a Legend الحلقة 4 مترجمة",
                                "thumbnail_url": "https://egydead.space/wp-content/uploads/2024/02/مسلسل-Messis-World-Cup-The-Rise-of-a-Legend-2024-مترجم-225x280.jpg"
                            },
                            {
                                "url": "/episode/مسلسل-messis-world-cup-the-rise-of-a-legend-الحلقة-3-مترجمة/",
                                "title": "مسلسل Messi’s World Cup The Rise of a Legend الحلقة 3 مترجمة",
                                "thumbnail_url": "https://egydead.space/wp-content/uploads/2024/02/مسلسل-Messis-World-Cup-The-Rise-of-a-Legend-2024-مترجم-225x280.jpg"
                            },
                            {
                                "url": "/episode/مسلسل-messis-world-cup-the-rise-of-a-legend-الحلقة-2-مترجمة/",
                                "title": "مسلسل Messi’s World Cup The Rise of a Legend الحلقة 2 مترجمة",
                                "thumbnail_url": "https://egydead.space/wp-content/uploads/2024/02/مسلسل-Messis-World-Cup-The-Rise-of-a-Legend-2024-مترجم-225x280.jpg"
                            },
                            {
                                "url": "/episode/مسلسل-messis-world-cup-the-rise-of-a-legend-الحلقة-1-مترجمة/",
                                "title": "مسلسل Messi’s World Cup The Rise of a Legend الحلقة 1 مترجمة",
                                "thumbnail_url": "https://egydead.space/wp-content/uploads/2024/02/مسلسل-Messis-World-Cup-The-Rise-of-a-Legend-2024-مترجم-225x280.jpg"
                            },
                            {
                                "url": "/season/مسلسل-messis-world-cup-the-rise-of-a-legend-2024-مترجم-كامل/",
                                "title": "مسلسل Messi’s World Cup The Rise of a Legend 2024 مترجم كامل",
                                "thumbnail_url": "https://egydead.space/wp-content/uploads/2024/02/مسلسل-Messis-World-Cup-The-Rise-of-a-Legend-2024-مترجم-كامل-207x280.jpg"
                            },
                            {
                                "url": "/مشاهدة-عرض-katt-williams-world-war-3-2022-مترجم/",
                                "title": "مشاهدة عرض Katt Williams World War 3 2022 مترجم",
                                "thumbnail_url": "https://egydead.space/wp-content/uploads/2024/01/عرض-Katt-Williams-World-War-3-2022-مترجم-210x280.jpg"
                            },
                            {
                                "url": "/فيلم-leave-the-world-behind-2023-مترجم/",
                                "title": "مشاهدة فيلم Leave the World Behind 2023 مترجم",
                                "thumbnail_url": "https://egydead.space/wp-content/uploads/2023/12/فيلم-Leave-the-World-Behind-2023-مترجم-210x280.jpg"
                            },
                            {
                                "url": "/season/مسلسل-war-of-the-worlds-الموسم-الثالث-مترجم-كامل/",
                                "title": "مسلسل War of the Worlds الموسم الثالث مترجم كامل",
                                "thumbnail_url": "https://egydead.space/wp-content/uploads/2022/09/مسلسل-War-of-the-Worlds-الموسم-الثالث-210x280.jpg"
                            },
                            {
                                "url": "/season/مسلسل-captains-of-the-world-2023-مترجم-كامل/",
                                "title": "مسلسل Captains of the World 2023 مترجم كامل",
                                "thumbnail_url": "https://egydead.space/wp-content/uploads/2023/12/مسلسل-Captains-of-the-World-2023-مترجم-كامل-225x280.jpg"
                            },
                            {
                                "url": "/episode/مسلسل-captains-of-the-world-الحلقة-6-مترجمة/",
                                "title": "مسلسل Captains of the World الحلقة 6 مترجمة",
                                "thumbnail_url": "https://egydead.space/wp-content/uploads/2023/12/مسلسل-Captains-of-the-World-2023-مترجم-كامل-225x280.jpg"
                            },
                            {
                                "url": "/episode/مسلسل-captains-of-the-world-الحلقة-5-مترجمة/",
                                "title": "مسلسل Captains of the World الحلقة 5 مترجمة",
                                "thumbnail_url": "https://egydead.space/wp-content/uploads/2023/12/مسلسل-Captains-of-the-World-2023-مترجم-كامل-225x280.jpg"
                            },
                            {
                                "url": "/episode/مسلسل-captains-of-the-world-الحلقة-4-مترجمة/",
                                "title": "مسلسل Captains of the World الحلقة 4 مترجمة",
                                "thumbnail_url": "https://egydead.space/wp-content/uploads/2023/12/مسلسل-Captains-of-the-World-2023-مترجم-كامل-225x280.jpg"
                            },
                            {
                                "url": "/episode/مسلسل-captains-of-the-world-الحلقة-3-مترجمة/",
                                "title": "مسلسل Captains of the World الحلقة 3 مترجمة",
                                "thumbnail_url": "https://egydead.space/wp-content/uploads/2023/12/مسلسل-Captains-of-the-World-2023-مترجم-كامل-225x280.jpg"
                            },
                            {
                                "url": "/episode/مسلسل-captains-of-the-world-الحلقة-2-مترجمة/",
                                "title": "مسلسل Captains of the World الحلقة 2 مترجمة",
                                "thumbnail_url": "https://egydead.space/wp-content/uploads/2023/12/مسلسل-Captains-of-the-World-2023-مترجم-كامل-225x280.jpg"
                            },
                            {
                                "url": "/episode/مسلسل-captains-of-the-world-الحلقة-1-مترجمة/",
                                "title": "مسلسل Captains of the World الحلقة 1 مترجمة",
                                "thumbnail_url": "https://egydead.space/wp-content/uploads/2023/12/مسلسل-Captains-of-the-World-2023-مترجم-كامل-225x280.jpg"
                            },
                            {
                                "url": "/مشاهدة-فيلم-when-you-finish-saving-the-world-2022-مترجم/",
                                "title": "مشاهدة فيلم When You Finish Saving The World 2022 مترجم",
                                "thumbnail_url": "https://egydead.space/wp-content/uploads/2023/01/When-You-Finish-Saving-The-World-2022-187x280.jpg"
                            },
                            {
                                "url": "/مشاهدة-فيلم-trolls-2-world-tour-2020-مترجم/",
                                "title": "مشاهدة فيلم Trolls 2 World Tour 2020 مترجم",
                                "thumbnail_url": "https://egydead.space/wp-content/uploads/2020/04/فيلم-Trolls-World-Tour-2020-مترجم-198x280.jpg"
                            },
                            {
                                "url": "/episode/مسلسل-a-murder-at-the-end-of-the-world-الحلقة-7-مترجمة/",
                                "title": "مسلسل A Murder at the End of the World الحلقة 7 مترجمة",
                                "thumbnail_url": "https://egydead.space/wp-content/uploads/2023/11/مسلسل-A-Murder-at-the-End-of-the-World-204x280.jpg"
                            },
                            {
                                "url": "/season/مسلسل-carol-and-the-end-of-the-world-2023-مترجم-كامل/",
                                "title": "مسلسل Carol and The End of the World 2023 مترجم كامل",
                                "thumbnail_url": "https://egydead.space/wp-content/uploads/2023/12/مسلسل-Carol-The-End-of-the-World-مترجم-كامل-210x280.jpg"
                            },
                            {
                                "url": "/episode/مسلسل-carol-and-the-end-of-the-world-الحلقة-10-مترجمة/",
                                "title": "مسلسل Carol and The End of the World الحلقة 10 مترجمة",
                                "thumbnail_url": "https://egydead.space/wp-content/uploads/2023/12/مسلسل-Carol-The-End-of-the-World-مترجم-كامل-210x280.jpg"
                            },
                            {
                                "url": "/episode/مسلسل-carol-and-the-end-of-the-world-الحلقة-9-مترجمة/",
                                "title": "مسلسل Carol and The End of the World الحلقة 9 مترجمة",
                                "thumbnail_url": "https://egydead.space/wp-content/uploads/2023/12/مسلسل-Carol-The-End-of-the-World-مترجم-كامل-210x280.jpg"
                            },
                            {
                                "url": "/episode/مسلسل-carol-and-the-end-of-the-world-الحلقة-8-مترجمة/",
                                "title": "مسلسل Carol and The End of the World الحلقة 8 مترجمة",
                                "thumbnail_url": "https://egydead.space/wp-content/uploads/2023/12/مسلسل-Carol-The-End-of-the-World-مترجم-كامل-210x280.jpg"
                            },
                            {
                                "url": "/episode/مسلسل-carol-and-the-end-of-the-world-الحلقة-7-مترجمة/",
                                "title": "مسلسل Carol and The End of the World الحلقة 7 مترجمة",
                                "thumbnail_url": "https://egydead.space/wp-content/uploads/2023/12/مسلسل-Carol-The-End-of-the-World-مترجم-كامل-210x280.jpg"
                            },
                            {
                                "url": "/episode/مسلسل-carol-and-the-end-of-the-world-الحلقة-6-مترجمة/",
                                "title": "مسلسل Carol and The End of the World الحلقة 6 مترجمة",
                                "thumbnail_url": "https://egydead.space/wp-content/uploads/2023/12/مسلسل-Carol-The-End-of-the-World-مترجم-كامل-210x280.jpg"
                            },
                            {
                                "url": "/episode/مسلسل-carol-and-the-end-of-the-world-الحلقة-5-مترجمة/",
                                "title": "مسلسل Carol and The End of the World الحلقة 5 مترجمة",
                                "thumbnail_url": "https://egydead.space/wp-content/uploads/2023/12/مسلسل-Carol-The-End-of-the-World-مترجم-كامل-210x280.jpg"
                            },
                            {
                                "url": "/episode/مسلسل-carol-and-the-end-of-the-world-الحلقة-4-مترجمة/",
                                "title": "مسلسل Carol and The End of the World الحلقة 4 مترجمة",
                                "thumbnail_url": "https://egydead.space/wp-content/uploads/2023/12/مسلسل-Carol-The-End-of-the-World-مترجم-كامل-210x280.jpg"
                            },
                            {
                                "url": "/episode/مسلسل-carol-and-the-end-of-the-world-الحلقة-3-مترجمة/",
                                "title": "مسلسل Carol and The End of the World الحلقة 3 مترجمة",
                                "thumbnail_url": "https://egydead.space/wp-content/uploads/2023/12/مسلسل-Carol-The-End-of-the-World-مترجم-كامل-210x280.jpg"
                            },
                            {
                                "url": "/episode/مسلسل-carol-and-the-end-of-the-world-الحلقة-2-مترجمة/",
                                "title": "مسلسل Carol and The End of the World الحلقة 2 مترجمة",
                                "thumbnail_url": "https://egydead.space/wp-content/uploads/2023/12/مسلسل-Carol-The-End-of-the-World-مترجم-كامل-210x280.jpg"
                            },
                            {
                                "url": "/episode/مسلسل-carol-and-the-end-of-the-world-الحلقة-1-مترجمة/",
                                "title": "مسلسل Carol and The End of the World الحلقة 1 مترجمة",
                                "thumbnail_url": "https://egydead.space/wp-content/uploads/2023/12/مسلسل-Carol-The-End-of-the-World-مترجم-كامل-210x280.jpg"
                            },
                            {
                                "url": "/episode/مسلسل-a-murder-at-the-end-of-the-world-الحلقة-6-مترجمة/",
                                "title": "مسلسل A Murder at the End of the World الحلقة 6 مترجمة",
                                "thumbnail_url": "https://egydead.space/wp-content/uploads/2023/11/مسلسل-A-Murder-at-the-End-of-the-World-204x280.jpg"
                            },
                            {
                                "url": "/season/مسلسل-under-pressure-the-u-s-womens-world-cup-team-2023-مترجم-كامل/",
                                "title": "مسلسل Under Pressure The U S Women’s World Cup Team 2023 مترجم كامل",
                                "thumbnail_url": "https://egydead.space/wp-content/uploads/2023/12/مسلسل-Under-Pressure-The-U.S.-Womens-World-Cup-Team-مترجم-كامل-187x280.jpg"
                            },
                            {
                                "url": "/episode/مسلسل-under-pressure-the-u-s-womens-world-cup-team-الحلقة-4-مترجمة/",
                                "title": "مسلسل Under Pressure The U S Women’s World Cup Team الحلقة 4 مترجمة",
                                "thumbnail_url": "https://egydead.space/wp-content/uploads/2023/12/مسلسل-Under-Pressure-The-U.S.-Womens-World-Cup-Team-210x280.jpg"
                            },
                            {
                                "url": "/episode/مسلسل-under-pressure-the-u-s-womens-world-cup-team-الحلقة-3-مترجمة/",
                                "title": "مسلسل Under Pressure The U S Women’s World Cup Team الحلقة 3 مترجمة",
                                "thumbnail_url": "https://egydead.space/wp-content/uploads/2023/12/مسلسل-Under-Pressure-The-U.S.-Womens-World-Cup-Team-210x280.jpg"
                            },
                            {
                                "url": "/episode/مسلسل-under-pressure-the-u-s-womens-world-cup-team-الحلقة-2-مترجمة/",
                                "title": "مسلسل Under Pressure The U S Women’s World Cup Team الحلقة 2 مترجمة",
                                "thumbnail_url": "https://egydead.space/wp-content/uploads/2023/12/مسلسل-Under-Pressure-The-U.S.-Womens-World-Cup-Team-210x280.jpg"
                            },
                            {
                                "url": "/episode/مسلسل-under-pressure-the-u-s-womens-world-cup-team-الحلقة-1-مترجمة/",
                                "title": "مسلسل Under Pressure The U S Women’s World Cup Team الحلقة 1 مترجمة",
                                "thumbnail_url": "https://egydead.space/wp-content/uploads/2023/12/مسلسل-Under-Pressure-The-U.S.-Womens-World-Cup-Team-210x280.jpg"
                            },
                            {
                                "url": "/season/مسلسل-war-of-the-worlds-الموسم-الثاني-مترجم-كامل/",
                                "title": "مسلسل War of the Worlds الموسم الثاني مترجم كامل",
                                "thumbnail_url": "https://egydead.space/wp-content/uploads/2019/10/War-of-the-Worlds-Season-2-225x280.jpg"
                            },
                            {
                                "url": "/season/مسلسل-war-of-the-worlds-الموسم-الاول-مترجم-كامل/",
                                "title": "مسلسل War of the Worlds الموسم الاول مترجم كامل",
                                "thumbnail_url": "https://egydead.space/wp-content/uploads/2019/10/War-of-the-Worlds-Season-1-225x280.jpg"
                            },
                            {
                                "url": "/مشاهدة-فيلم-hello-world-2019-مترجم/",
                                "title": "مشاهدة فيلم Hello World 2019 مترجم",
                                "thumbnail_url": "https://egydead.space/wp-content/uploads/2023/12/فيلم-Hello-World-2019-مترجم-204x280.jpg"
                            },
                            {
                                "url": "/season/انمي-another-world-2019-مترجم-كامل/",
                                "title": "انمي Another World 2019 مترجم كامل",
                                "thumbnail_url": "https://egydead.space/wp-content/uploads/2020/04/انمي-Another-World-كاملة-226x280.jpg"
                            },
                            {
                                "url": "/مشاهدة-فيلم-the-worlds-first-christmas-2023-مترجم/",
                                "title": "مشاهدة فيلم The World’s First Christmas 2023 مترجم",
                                "thumbnail_url": "https://egydead.space/wp-content/uploads/2023/12/فيلم-The-Worlds-First-Christmas-2023-مترجم-197x280.jpg"
                            },
                            {
                                "url": "/season/مسلسل-world-war-ii-from-the-frontlines-2023-مترجم-كامل/",
                                "title": "مسلسل World War II From the Frontlines 2023 مترجم كامل",
                                "thumbnail_url": "https://egydead.space/wp-content/uploads/2023/12/مسلسل-World-War-II-From-the-Frontlines-مترجم-كامل-225x280.jpg"
                            },
                            {
                                "url": "/episode/مسلسل-world-war-ii-from-the-frontlines-الحلقة-6-مترجمة/",
                                "title": "مسلسل World War II From the Frontlines الحلقة 6 مترجمة",
                                "thumbnail_url": "https://egydead.space/wp-content/uploads/2023/12/مسلسل-World-War-II-From-the-Frontlines-مترجم-225x280.jpg"
                            },
                            {
                                "url": "/episode/مسلسل-world-war-ii-from-the-frontlines-الحلقة-5-مترجمة/",
                                "title": "مسلسل World War II From the Frontlines الحلقة 5 مترجمة",
                                "thumbnail_url": "https://egydead.space/wp-content/uploads/2023/12/مسلسل-World-War-II-From-the-Frontlines-مترجم-225x280.jpg"
                            },
                            {
                                "url": "/episode/مسلسل-world-war-ii-from-the-frontlines-الحلقة-4-مترجمة/",
                                "title": "مسلسل World War II From the Frontlines الحلقة 4 مترجمة",
                                "thumbnail_url": "https://egydead.space/wp-content/uploads/2023/12/مسلسل-World-War-II-From-the-Frontlines-مترجم-225x280.jpg"
                            },
                            {
                                "url": "/episode/مسلسل-world-war-ii-from-the-frontlines-الحلقة-3-مترجمة/",
                                "title": "مسلسل World War II From the Frontlines الحلقة 3 مترجمة",
                                "thumbnail_url": "https://egydead.space/wp-content/uploads/2023/12/مسلسل-World-War-II-From-the-Frontlines-مترجم-225x280.jpg"
                            },
                            {
                                "url": "/episode/مسلسل-world-war-ii-from-the-frontlines-الحلقة-2-مترجمة/",
                                "title": "مسلسل World War II From the Frontlines الحلقة 2 مترجمة",
                                "thumbnail_url": "https://egydead.space/wp-content/uploads/2023/12/مسلسل-World-War-II-From-the-Frontlines-مترجم-225x280.jpg"
                            },
                            {
                                "url": "/episode/مسلسل-world-war-ii-from-the-frontlines-الحلقة-1-مترجمة/",
                                "title": "مسلسل World War II From the Frontlines الحلقة 1 مترجمة",
                                "thumbnail_url": "https://egydead.space/wp-content/uploads/2023/12/مسلسل-World-War-II-From-the-Frontlines-مترجم-225x280.jpg"
                            },
                            {
                                "url": "/season/انمي-worlds-end-harem-2021-مترجم-كامل/",
                                "title": "انمي World’s End Harem 2021 مترجم كامل",
                                "thumbnail_url": "https://egydead.space/wp-content/uploads/2021/09/انمي-Worlds-End-Harem-2021-مترجم-كامل-210x280.jpg"
                            }
                        ],
                        "hasNextPage": true
                    }
                ],
                "passed": true
            },
            "details": {
                "result": {
                    "url": "/episode/مسلسل-the-rookie-الموسم-السادس-الحلقة-5-مترجمة/",
                    "title": "مسلسل The Rookie الموسم السادس الحلقة 5 مترجمة",
                    "artist": "مسلسلات اجنبي",
                    "author": "أمريكا",
                    "description": "يحاول (جون نولان) السير في بداية جديدة في حياته بعد تعرضه لحادثة كبيرة، حيث يسعى للانضمام إلى شرطة لوس أنجلوس لتحقيق أحلامه، ولكنه يعاني من التجاهل من الجميع ظنًا منهم أنه يعاني من أزمة منتصف العمر.",
                    "genre": "اكشن, جريمة, دراما, الأنجليزية, 2024",
                    "status": 1,
                    "status_name": "ONGOING",
                    "thumbnail_url": "https://egydead.space/wp-content/uploads/2024/02/مسلسل-The-Rookie-الموسم-السادس.jpg",
                    "initialized": true
                },
                "passed": true
            },
            "episodes": {
                "result": [
                    {
                        "url": "/episode/مسلسل-the-rookie-الموسم-السادس-الحلقة-5-مترجمة/",
                        "name": "الموسم السادس حلقه 5",
                        "episode_number": 5.0
                    },
                    {
                        "url": "/episode/مسلسل-the-rookie-الموسم-السادس-الحلقة-4-مترجمة/",
                        "name": "الموسم السادس حلقه 4",
                        "episode_number": 4.0
                    }
                ],
                "passed": true
            },
            "videos": {
                "result": [
                    {
                        "url": "https://udrlvroyoqvy.sw-cdnstreamwish.com/hls2/01/03499/emumsvs9dcop_,n,h,.urlset/index-f1-v1-a1.m3u8?t=cndTj3hP_5QqbXGyYQWQHhEhpiKdRieLetoSc0cQkz4&s=1712168138&e=129600&f=17497238&srv=mnnx3x8e5xk&i=0.4&sp=500&p1=mnnx3x8e5xk&p2=mnnx3x8e5xk&asn=8075",
                        "quality": "StreamWish - 480p",
                        "videoUrl": "https://udrlvroyoqvy.sw-cdnstreamwish.com/hls2/01/03499/emumsvs9dcop_,n,h,.urlset/index-f1-v1-a1.m3u8?t=cndTj3hP_5QqbXGyYQWQHhEhpiKdRieLetoSc0cQkz4&s=1712168138&e=129600&f=17497238&srv=mnnx3x8e5xk&i=0.4&sp=500&p1=mnnx3x8e5xk&p2=mnnx3x8e5xk&asn=8075",
                        "headers": {
                            "User-Agent": "Mozilla/5.0 (X11; Linux x86_64; rv:121.0) Gecko/20100101 Firefox/121.0",
                            "Accept": "*/*",
                            "Origin": "https://trgsfjll.sbs",
                            "Referer": "https://trgsfjll.sbs/e/emumsvs9dcop"
                        }
                    },
                    {
                        "url": "https://udrlvroyoqvy.sw-cdnstreamwish.com/hls2/01/03499/emumsvs9dcop_,n,h,.urlset/index-f2-v1-a1.m3u8?t=cndTj3hP_5QqbXGyYQWQHhEhpiKdRieLetoSc0cQkz4&s=1712168138&e=129600&f=17497238&srv=mnnx3x8e5xk&i=0.4&sp=500&p1=mnnx3x8e5xk&p2=mnnx3x8e5xk&asn=8075",
                        "quality": "StreamWish - 720p",
                        "videoUrl": "https://udrlvroyoqvy.sw-cdnstreamwish.com/hls2/01/03499/emumsvs9dcop_,n,h,.urlset/index-f2-v1-a1.m3u8?t=cndTj3hP_5QqbXGyYQWQHhEhpiKdRieLetoSc0cQkz4&s=1712168138&e=129600&f=17497238&srv=mnnx3x8e5xk&i=0.4&sp=500&p1=mnnx3x8e5xk&p2=mnnx3x8e5xk&asn=8075",
                        "headers": {
                            "User-Agent": "Mozilla/5.0 (X11; Linux x86_64; rv:121.0) Gecko/20100101 Firefox/121.0",
                            "Accept": "*/*",
                            "Origin": "https://trgsfjll.sbs",
                            "Referer": "https://trgsfjll.sbs/e/emumsvs9dcop"
                        }
                    }
                ],
                "passed": true
            }
        }
    }
]