[
    {
        "name": "AnimePahe",
        "results": {
            "popular": {
                "result": [
                    {
                        "animes": [
                            {
                                "url": "/anime/?anime_id=4756",
                                "title": "Yu☆Gi☆Oh! Go Rush!!",
                                "artist": "entameSubs",
                                "thumbnail_url": "https://i.animepahe.com/snapshots/d86fbed62b7b4c69484b068537090967be205c4ce243917667dc85e28dee6001.jpg"
                            },
                            {
                                "url": "/anime/?anime_id=5288",
                                "title": "Helck",
                                "artist": "SubsPlease",
                                "thumbnail_url": "https://i.animepahe.com/snapshots/3d4610940194d81751d11de312160e74831c960db09112eb351398df0c30f2ef.jpg"
                            },
                            {
                                "url": "/anime/?anime_id=5270",
                                "title": "Suki na Ko ga Megane wo Wasureta",
                                "artist": "SubsPlease",
                                "thumbnail_url": "https://i.animepahe.com/snapshots/e4c058b0a810532716c7170fdeab0e1a45260d0e77d21c93a818c42a0b5d96b8.jpg"
                            },
                            {
                                "url": "/anime/?anime_id=5279",
                                "title": "Yumemiru Danshi wa Genjitsushugisha",
                                "artist": "SubsPlease",
                                "thumbnail_url": "https://i.animepahe.com/snapshots/93ee6274ec8a950404f2c300371b4c32a7fb9d88bde8c85bda4390694dac0ec5.jpg"
                            },
                            {
                                "url": "/anime/?anime_id=5295",
                                "title": "Okashi na Tensei",
                                "artist": "SubsPlease",
                                "thumbnail_url": "https://i.animepahe.com/snapshots/8b54955cdea68948a702174da35de6d52549105835928b26020828bf303f1172.jpg"
                            },
                            {
                                "url": "/anime/?anime_id=5178",
                                "title": "Yi Nian Yong Heng: Chuan Cheng Pian",
                                "artist": "Hall_of_C",
                                "thumbnail_url": "https://i.animepahe.com/snapshots/98e6e8760bd82a4207c6aa3af8a728257eae1bc42dd699a643ec81294efdb64c.jpg"
                            },
                            {
                                "url": "/anime/?anime_id=5298",
                                "title": "Mononogatari 2nd Season",
                                "artist": "SubsPlease",
                                "thumbnail_url": "https://i.animepahe.com/snapshots/f73d74c3031fac0ef0877ea14ca292192f64f159c128d616a2159a7aaeb41b32.jpg"
                            },
                            {
                                "url": "/anime/?anime_id=5299",
                                "title": "Lv1 Maou to One Room Yuusha",
                                "artist": "SubsPlease",
                                "thumbnail_url": "https://i.animepahe.com/snapshots/36dbeea9c02610f61aeebfd84b3672937a8ba9d442425d7ecb35e25cc1aaf94c.jpg"
                            },
                            {
                                "url": "/anime/?anime_id=5264",
                                "title": "Masamune-kun no Revenge R",
                                "artist": "Yameii",
                                "thumbnail_url": "https://i.animepahe.com/snapshots/01b5c68492a8d774198cde2ee8b9d8426241eb17ada31ef4bea4bc3ac3861fea.jpg"
                            },
                            {
                                "url": "/anime/?anime_id=5052",
                                "title": "NieR:Automata Ver1.1a",
                                "artist": "SubsPlease",
                                "thumbnail_url": "https://i.animepahe.com/snapshots/ea9dcd0acadd84a99b59347415f4d1ab4a9ad39d5fa8047430157d1e2621836b.jpg"
                            },
                            {
                                "url": "/anime/?anime_id=5263",
                                "title": "Mushoku Tensei II: Isekai Ittara Honki Dasu",
                                "artist": "MTBB",
                                "thumbnail_url": "https://i.animepahe.com/snapshots/09030be8c553ba0b1cb0441e486ca60038d7020a440c82759ffeccd34b39ca72.jpg"
                            },
                            {
                                "url": "/anime/?anime_id=5140",
                                "title": "Chibi Maruko-chan",
                                "artist": "MaruChanSubs",
                                "thumbnail_url": "https://i.animepahe.com/snapshots/15332f5e7fb5fb5a981a26fec2f945f5690f55e0e0aa30e15e75684be3e500a4.jpg"
                            }
                        ],
                        "hasNextPage": true
                    }
                ],
                "passed": true
            },
            "latest": {
                "result": [
                    {
                        "animes": [
                            {
                                "url": "/anime/?anime_id=4756",
                                "title": "Yu☆Gi☆Oh! Go Rush!!",
                                "artist": "entameSubs",
                                "thumbnail_url": "https://i.animepahe.com/snapshots/d86fbed62b7b4c69484b068537090967be205c4ce243917667dc85e28dee6001.jpg"
                            },
                            {
                                "url": "/anime/?anime_id=5288",
                                "title": "Helck",
                                "artist": "SubsPlease",
                                "thumbnail_url": "https://i.animepahe.com/snapshots/3d4610940194d81751d11de312160e74831c960db09112eb351398df0c30f2ef.jpg"
                            },
                            {
                                "url": "/anime/?anime_id=5270",
                                "title": "Suki na Ko ga Megane wo Wasureta",
                                "artist": "SubsPlease",
                                "thumbnail_url": "https://i.animepahe.com/snapshots/e4c058b0a810532716c7170fdeab0e1a45260d0e77d21c93a818c42a0b5d96b8.jpg"
                            },
                            {
                                "url": "/anime/?anime_id=5279",
                                "title": "Yumemiru Danshi wa Genjitsushugisha",
                                "artist": "SubsPlease",
                                "thumbnail_url": "https://i.animepahe.com/snapshots/93ee6274ec8a950404f2c300371b4c32a7fb9d88bde8c85bda4390694dac0ec5.jpg"
                            },
                            {
                                "url": "/anime/?anime_id=5295",
                                "title": "Okashi na Tensei",
                                "artist": "SubsPlease",
                                "thumbnail_url": "https://i.animepahe.com/snapshots/8b54955cdea68948a702174da35de6d52549105835928b26020828bf303f1172.jpg"
                            },
                            {
                                "url": "/anime/?anime_id=5178",
                                "title": "Yi Nian Yong Heng: Chuan Cheng Pian",
                                "artist": "Hall_of_C",
                                "thumbnail_url": "https://i.animepahe.com/snapshots/98e6e8760bd82a4207c6aa3af8a728257eae1bc42dd699a643ec81294efdb64c.jpg"
                            },
                            {
                                "url": "/anime/?anime_id=5298",
                                "title": "Mononogatari 2nd Season",
                                "artist": "SubsPlease",
                                "thumbnail_url": "https://i.animepahe.com/snapshots/f73d74c3031fac0ef0877ea14ca292192f64f159c128d616a2159a7aaeb41b32.jpg"
                            },
                            {
                                "url": "/anime/?anime_id=5299",
                                "title": "Lv1 Maou to One Room Yuusha",
                                "artist": "SubsPlease",
                                "thumbnail_url": "https://i.animepahe.com/snapshots/36dbeea9c02610f61aeebfd84b3672937a8ba9d442425d7ecb35e25cc1aaf94c.jpg"
                            },
                            {
                                "url": "/anime/?anime_id=5264",
                                "title": "Masamune-kun no Revenge R",
                                "artist": "Yameii",
                                "thumbnail_url": "https://i.animepahe.com/snapshots/01b5c68492a8d774198cde2ee8b9d8426241eb17ada31ef4bea4bc3ac3861fea.jpg"
                            },
                            {
                                "url": "/anime/?anime_id=5052",
                                "title": "NieR:Automata Ver1.1a",
                                "artist": "SubsPlease",
                                "thumbnail_url": "https://i.animepahe.com/snapshots/ea9dcd0acadd84a99b59347415f4d1ab4a9ad39d5fa8047430157d1e2621836b.jpg"
                            },
                            {
                                "url": "/anime/?anime_id=5263",
                                "title": "Mushoku Tensei II: Isekai Ittara Honki Dasu",
                                "artist": "MTBB",
                                "thumbnail_url": "https://i.animepahe.com/snapshots/09030be8c553ba0b1cb0441e486ca60038d7020a440c82759ffeccd34b39ca72.jpg"
                            },
                            {
                                "url": "/anime/?anime_id=5140",
                                "title": "Chibi Maruko-chan",
                                "artist": "MaruChanSubs",
                                "thumbnail_url": "https://i.animepahe.com/snapshots/15332f5e7fb5fb5a981a26fec2f945f5690f55e0e0aa30e15e75684be3e500a4.jpg"
                            }
                        ],
                        "hasNextPage": true
                    }
                ],
                "passed": true
            },
            "search": {
                "result": [
                    {
                        "animes": [
                            {
                                "url": "/anime/?anime_id=119",
                                "title": "World Trigger",
                                "thumbnail_url": "https://i.animepahe.com/posters/5a3bd9bf6b59f52791ed7b7c05a300a1b9e9007a625d85124ccd7b2284cba8a0.jpg"
                            },
                            {
                                "url": "/anime/?anime_id=2064",
                                "title": "World Fool News (TV)",
                                "thumbnail_url": "https://i.animepahe.com/posters/fa9d124c722e9299a10cb95a7f21a020c743aee11fffdfc70e359174a6e21fc9.jpg"
                            },
                            {
                                "url": "/anime/?anime_id=2043",
                                "title": "World Fool News (TV) Part II",
                                "thumbnail_url": "https://i.animepahe.com/posters/0073b9c98ead3b7f10842dbec19670b5f21fddbc63404466bae6b833c2328195.jpg"
                            },
                            {
                                "url": "/anime/?anime_id=4524",
                                "title": "World Trigger 3rd Season",
                                "thumbnail_url": "https://i.animepahe.com/posters/342aeeeafea0be4d7b0d073ea0911ad86bea88261c782ea64211c470073eab08.jpg"
                            },
                            {
                                "url": "/anime/?anime_id=4175",
                                "title": "World Trigger 2nd Season",
                                "thumbnail_url": "https://i.animepahe.com/posters/50d7865d198d0a2d7faee377b50698e3a16934f63c345dad425975146ac03778.jpg"
                            },
                            {
                                "url": "/anime/?anime_id=4200",
                                "title": "World Witches Hasshin Shimasu!",
                                "thumbnail_url": "https://i.animepahe.com/posters/043989368c94192bfdb1843bbf32ce2a798c3acc82b1deea803fd02e3bd67b07.jpg"
                            },
                            {
                                "url": "/anime/?anime_id=5229",
                                "title": "World Dai Star",
                                "thumbnail_url": "https://i.animepahe.com/posters/e9a0985f593a33302d983d125b3fd44d1124c540176fcfad6296a0b819709319.jpg"
                            },
                            {
                                "url": "/anime/?anime_id=3709",
                                "title": "World Fool News",
                                "thumbnail_url": "https://i.animepahe.com/posters/b41c8c670b99fbb48485ce830a2b30236806c701bec41fcb249c22cd39287fdb.jpg"
                            }
                        ],
                        "hasNextPage": false
                    }
                ],
                "passed": true
            },
            "details": {
                "result": {
                    "url": "/anime/?anime_id=4756",
                    "title": "Yu☆Gi☆Oh! Go Rush!!",
                    "author": "Bridge",
                    "description": "After inheriting the company from their parents, siblings Yuuhi and Yuamu Oudou have started to work at Ultraterrestrial Trouble Solutions, an organization that hunts aliens. Although they have never encountered aliens before, Yuuhi is desperate to meet one as he believes that an alien has stolen his important item called the \"Earthdamar.\" One day, while searching for extraterrestrial creatures, Yuuhi and Yuamu find a strange spot in the forest where many trees have fallen, forming a scenery similar to a crop circle. As they venture further, they discover a mysterious spaceship and enter it out of curiosity. To their surprise, they come across Yudias Velgear, an alien from the Velgear Star Cluster. As it turns out, Yudias is seeking to learn about Rush Duel—a card game popular among elementary school students—as he believes that it will save his home from a long war. With the siblings agreeing to teach Yudias about Rush Duel, they eventually realize that their first contact with an alien may not be a random coincidence.\n\nSynonyms: Yuu Gi Ou: Go Rush!!",
                    "genre": "Action, Fantasy",
                    "status": 1,
                    "status_name": "ONGOING",
                    "thumbnail_url": "https://i.animepahe.ru/posters/878719f520f143d6871468326bff47a3a85eff5d651de268eb167c27a35173e6.jpg",
                    "initialized": true
                },
                "passed": true
            },
            "episodes": {
                "result": [
                    {
                        "url": "/play/5705e78b-4323-b3cf-9730-30e7c185efa0/6d81ad2b5a38d8698e42f7f86b53d527525e91c867d7636353f156c6f80f2558",
                        "name": "Episode 68",
                        "date_upload": 1690333289000,
                        "episode_number": 68.0
                    },
                    {
                        "url": "/play/5705e78b-4323-b3cf-9730-30e7c185efa0/991f9f7926a3a08afd0939a52a663b183a42126d4762d12f4b8481e78d06184c",
                        "name": "Episode 67",
                        "date_upload": 1689808327000,
                        "episode_number": 67.0
                    }
                ],
                "passed": true
            },
            "videos": {
                "result": [
                    {
                        "url": "https://na-99.files.nextcdn.org/get/99/01/fb200e148afb82b73806e236025ec367f4d241c1546073775404ae9cf33001da?file=AnimePahe_Yu-Gi-Oh_-_Go_Rush_-_68_720p_entameSubs.mp4&token=icfu_gj31y5rmI3gSsU5OQ&expires=1690347945",
                        "quality": "entameSubs · 720p",
                        "videoUrl": "https://na-99.files.nextcdn.org/get/99/01/fb200e148afb82b73806e236025ec367f4d241c1546073775404ae9cf33001da?file=AnimePahe_Yu-Gi-Oh_-_Go_Rush_-_68_720p_entameSubs.mp4&token=icfu_gj31y5rmI3gSsU5OQ&expires=1690347945"
                    },
                    {
                        "url": "https://na-99.files.nextcdn.org/get/99/01/752f56201991c1b8801258017d8c1862cf41575b36746d64d494c13fffe83141?file=AnimePahe_Yu-Gi-Oh_-_Go_Rush_-_68_360p_entameSubs.mp4&token=MdUgbS_1DH3_D7oDXU-EQg&expires=1690347944",
                        "quality": "entameSubs · 360p",
                        "videoUrl": "https://na-99.files.nextcdn.org/get/99/01/752f56201991c1b8801258017d8c1862cf41575b36746d64d494c13fffe83141?file=AnimePahe_Yu-Gi-Oh_-_Go_Rush_-_68_360p_entameSubs.mp4&token=MdUgbS_1DH3_D7oDXU-EQg&expires=1690347944"
                    }
                ],
                "passed": true
            }
        }
    }
]