[
    {
        "name": "WCOStream (EN)",
        "results": {
            "popular": {
                "result": [
                    {
                        "animes": [
                            {
                                "url": "{\"title\":\"Kit n Kate\",\"url\":\"/kit-n-kate-episode-1-me-oh-my-blueberry-pie-mad-mad-mad-time-to-climb-the-catelephant\",\"thumbnailUrl\":\"https://cdn.animationexplore.com/catimg/933628.jpg\"}",
                                "title": "Kit n Kate",
                                "thumbnail_url": "https://cdn.animationexplore.com/catimg/933628.jpg"
                            },
                            {
                                "url": "{\"title\":\"I Was Reincarnated as the 7th Prince so I Can Take My Time Perfecting My Magical Ability\",\"url\":\"/i-was-reincarnated-as-the-7th-prince-so-i-can-take-my-time-perfecting-my-magical-ability-episode-12-english-dubbed\",\"thumbnailUrl\":\"https://cdn.animationexplore.com/catimg/933579.jpg\"}",
                                "title": "I Was Reincarnated as the 7th Prince so I Can Take My Time Perfecting My Magical Ability",
                                "thumbnail_url": "https://cdn.animationexplore.com/catimg/933579.jpg"
                            },
                            {
                                "url": "{\"title\":\"Chillin' in Another World With Level 2 Super Cheat Powers\",\"url\":\"/chillin-in-another-world-with-level-2-super-cheat-powers-episode-11-english-dubbed\",\"thumbnailUrl\":\"https://cdn.animationexplore.com/catimg/933589.jpg\"}",
                                "title": "Chillin' in Another World With Level 2 Super Cheat Powers",
                                "thumbnail_url": "https://cdn.animationexplore.com/catimg/933589.jpg"
                            },
                            {
                                "url": "{\"title\":\"Spice and Wolf: Merchant Meets the Wise Wolf\",\"url\":\"/spice-and-wolf-merchant-meets-the-wise-wolf-episode-11-english-dubbed\",\"thumbnailUrl\":\"https://cdn.animationexplore.com/catimg/933580.jpg\"}",
                                "title": "Spice and Wolf: Merchant Meets the Wise Wolf",
                                "thumbnail_url": "https://cdn.animationexplore.com/catimg/933580.jpg"
                            },
                            {
                                "url": "{\"title\":\"Tsukimichi: Moonlight Fantasy Season 2\",\"url\":\"/tsukimichi-moonlight-fantasy-season-2-episode-24-english-dubbed\",\"thumbnailUrl\":\"https://cdn.animationexplore.com/catimg/931699.jpg\"}",
                                "title": "Tsukimichi: Moonlight Fantasy Season 2",
                                "thumbnail_url": "https://cdn.animationexplore.com/catimg/931699.jpg"
                            },
                            {
                                "url": "{\"title\":\"The Vexations of a Shut-In Vampire Princess\",\"url\":\"/the-vexations-of-a-shut-in-vampire-princess-episode-12-english-dubbed\",\"thumbnailUrl\":\"https://cdn.animationexplore.com/catimg/933578.jpg\"}",
                                "title": "The Vexations of a Shut-In Vampire Princess",
                                "thumbnail_url": "https://cdn.animationexplore.com/catimg/933578.jpg"
                            },
                            {
                                "url": "{\"title\":\"Gimai Seikatsu\",\"url\":\"/gimai-seikatsu-episode-1-english-subbed\",\"thumbnailUrl\":\"https://cdn.animationexplore.com/catimg/933625.jpg\"}",
                                "title": "Gimai Seikatsu",
                                "thumbnail_url": "https://cdn.animationexplore.com/catimg/933625.jpg"
                            },
                            {
                                "url": "{\"title\":\"Shinmai Ossan Boukensha, Saikyou Party ni Shinu hodo Kitaerarete Muteki ni Naru.\",\"url\":\"/shinmai-ossan-boukensha-saikyou-party-ni-shinu-hodo-kitaerarete-muteki-ni-naru-episode-1-english-subbed\",\"thumbnailUrl\":\"https://cdn.animationexplore.com/catimg/933626.jpg\"}",
                                "title": "Shinmai Ossan Boukensha, Saikyou Party ni Shinu hodo Kitaerarete Muteki ni Naru.",
                                "thumbnail_url": "https://cdn.animationexplore.com/catimg/933626.jpg"
                            },
                            {
                                "url": "{\"title\":\"Ookami to Koushinryou: Merchant Meets the Wise Wolf\",\"url\":\"/ookami-to-koushinryou-merchant-meets-the-wise-wolf-episode-14-english-subbed\",\"thumbnailUrl\":\"https://cdn.animationexplore.com/catimg/933532.jpg\"}",
                                "title": "Ookami to Koushinryou: Merchant Meets the Wise Wolf",
                                "thumbnail_url": "https://cdn.animationexplore.com/catimg/933532.jpg"
                            },
                            {
                                "url": "{\"title\":\"My Adventures with Superman Season 2\",\"url\":\"/my-adventures-with-superman-season-2-episode-7-olsens-eleven\",\"thumbnailUrl\":\"https://cdn.animationexplore.com/catimg/932995.jpg\"}",
                                "title": "My Adventures with Superman Season 2",
                                "thumbnail_url": "https://cdn.animationexplore.com/catimg/932995.jpg"
                            },
                            {
                                "url": "{\"title\":\"WondLa\",\"url\":\"/wondla-episode-7-ruins\",\"thumbnailUrl\":\"https://cdn.animationexplore.com/catimg/933627.jpg\"}",
                                "title": "WondLa",
                                "thumbnail_url": "https://cdn.animationexplore.com/catimg/933627.jpg"
                            },
                            {
                                "url": "{\"title\":\"WondLa\",\"url\":\"/wondla-episode-1-doors\",\"thumbnailUrl\":\"https://cdn.animationexplore.com/catimg/933627.jpg\"}",
                                "title": "WondLa",
                                "thumbnail_url": "https://cdn.animationexplore.com/catimg/933627.jpg"
                            },
                            {
                                "url": "{\"title\":\"Shy Season 2\",\"url\":\"/shy-season-2-episode-1-english-subbed\",\"thumbnailUrl\":\"https://cdn.animationexplore.com/catimg/933167.jpg\"}",
                                "title": "Shy Season 2",
                                "thumbnail_url": "https://cdn.animationexplore.com/catimg/933167.jpg"
                            },
                            {
                                "url": "{\"title\":\"Mission Yozakura Family\",\"url\":\"/mission-yozakura-family-episode-3-english-dubbed\",\"thumbnailUrl\":\"https://cdn.animationexplore.com/catimg/933612.jpg\"}",
                                "title": "Mission Yozakura Family",
                                "thumbnail_url": "https://cdn.animationexplore.com/catimg/933612.jpg"
                            },
                            {
                                "url": "{\"title\":\"The Duke of Death and His Maid Season 3\",\"url\":\"/the-duke-of-death-and-his-maid-season-3-episode-11-english-dubbed\",\"thumbnailUrl\":\"https://cdn.animationexplore.com/catimg/908768.jpg\"}",
                                "title": "The Duke of Death and His Maid Season 3",
                                "thumbnail_url": "https://cdn.animationexplore.com/catimg/908768.jpg"
                            },
                            {
                                "url": "{\"title\":\"Vampire Dormitory\",\"url\":\"/vampire-dormitory-episode-11-english-dubbed\",\"thumbnailUrl\":\"https://cdn.animationexplore.com/catimg/933588.jpg\"}",
                                "title": "Vampire Dormitory",
                                "thumbnail_url": "https://cdn.animationexplore.com/catimg/933588.jpg"
                            }
                        ],
                        "hasNextPage": false
                    }
                ],
                "passed": true
            },
            "latest": {
                "result": [
                    {
                        "animes": [
                            {
                                "url": "{\"title\":\"Kit n Kate\",\"url\":\"/kit-n-kate-episode-1-me-oh-my-blueberry-pie-mad-mad-mad-time-to-climb-the-catelephant\",\"thumbnailUrl\":\"https://cdn.animationexplore.com/catimg/933628.jpg\"}",
                                "title": "Kit n Kate",
                                "thumbnail_url": "https://cdn.animationexplore.com/catimg/933628.jpg"
                            },
                            {
                                "url": "{\"title\":\"I Was Reincarnated as the 7th Prince so I Can Take My Time Perfecting My Magical Ability\",\"url\":\"/i-was-reincarnated-as-the-7th-prince-so-i-can-take-my-time-perfecting-my-magical-ability-episode-12-english-dubbed\",\"thumbnailUrl\":\"https://cdn.animationexplore.com/catimg/933579.jpg\"}",
                                "title": "I Was Reincarnated as the 7th Prince so I Can Take My Time Perfecting My Magical Ability",
                                "thumbnail_url": "https://cdn.animationexplore.com/catimg/933579.jpg"
                            },
                            {
                                "url": "{\"title\":\"Chillin' in Another World With Level 2 Super Cheat Powers\",\"url\":\"/chillin-in-another-world-with-level-2-super-cheat-powers-episode-11-english-dubbed\",\"thumbnailUrl\":\"https://cdn.animationexplore.com/catimg/933589.jpg\"}",
                                "title": "Chillin' in Another World With Level 2 Super Cheat Powers",
                                "thumbnail_url": "https://cdn.animationexplore.com/catimg/933589.jpg"
                            },
                            {
                                "url": "{\"title\":\"Spice and Wolf: Merchant Meets the Wise Wolf\",\"url\":\"/spice-and-wolf-merchant-meets-the-wise-wolf-episode-11-english-dubbed\",\"thumbnailUrl\":\"https://cdn.animationexplore.com/catimg/933580.jpg\"}",
                                "title": "Spice and Wolf: Merchant Meets the Wise Wolf",
                                "thumbnail_url": "https://cdn.animationexplore.com/catimg/933580.jpg"
                            },
                            {
                                "url": "{\"title\":\"Tsukimichi: Moonlight Fantasy Season 2\",\"url\":\"/tsukimichi-moonlight-fantasy-season-2-episode-24-english-dubbed\",\"thumbnailUrl\":\"https://cdn.animationexplore.com/catimg/931699.jpg\"}",
                                "title": "Tsukimichi: Moonlight Fantasy Season 2",
                                "thumbnail_url": "https://cdn.animationexplore.com/catimg/931699.jpg"
                            },
                            {
                                "url": "{\"title\":\"The Vexations of a Shut-In Vampire Princess\",\"url\":\"/the-vexations-of-a-shut-in-vampire-princess-episode-12-english-dubbed\",\"thumbnailUrl\":\"https://cdn.animationexplore.com/catimg/933578.jpg\"}",
                                "title": "The Vexations of a Shut-In Vampire Princess",
                                "thumbnail_url": "https://cdn.animationexplore.com/catimg/933578.jpg"
                            },
                            {
                                "url": "{\"title\":\"Gimai Seikatsu\",\"url\":\"/gimai-seikatsu-episode-1-english-subbed\",\"thumbnailUrl\":\"https://cdn.animationexplore.com/catimg/933625.jpg\"}",
                                "title": "Gimai Seikatsu",
                                "thumbnail_url": "https://cdn.animationexplore.com/catimg/933625.jpg"
                            },
                            {
                                "url": "{\"title\":\"Shinmai Ossan Boukensha, Saikyou Party ni Shinu hodo Kitaerarete Muteki ni Naru.\",\"url\":\"/shinmai-ossan-boukensha-saikyou-party-ni-shinu-hodo-kitaerarete-muteki-ni-naru-episode-1-english-subbed\",\"thumbnailUrl\":\"https://cdn.animationexplore.com/catimg/933626.jpg\"}",
                                "title": "Shinmai Ossan Boukensha, Saikyou Party ni Shinu hodo Kitaerarete Muteki ni Naru.",
                                "thumbnail_url": "https://cdn.animationexplore.com/catimg/933626.jpg"
                            },
                            {
                                "url": "{\"title\":\"Ookami to Koushinryou: Merchant Meets the Wise Wolf\",\"url\":\"/ookami-to-koushinryou-merchant-meets-the-wise-wolf-episode-14-english-subbed\",\"thumbnailUrl\":\"https://cdn.animationexplore.com/catimg/933532.jpg\"}",
                                "title": "Ookami to Koushinryou: Merchant Meets the Wise Wolf",
                                "thumbnail_url": "https://cdn.animationexplore.com/catimg/933532.jpg"
                            },
                            {
                                "url": "{\"title\":\"My Adventures with Superman Season 2\",\"url\":\"/my-adventures-with-superman-season-2-episode-7-olsens-eleven\",\"thumbnailUrl\":\"https://cdn.animationexplore.com/catimg/932995.jpg\"}",
                                "title": "My Adventures with Superman Season 2",
                                "thumbnail_url": "https://cdn.animationexplore.com/catimg/932995.jpg"
                            },
                            {
                                "url": "{\"title\":\"WondLa\",\"url\":\"/wondla-episode-7-ruins\",\"thumbnailUrl\":\"https://cdn.animationexplore.com/catimg/933627.jpg\"}",
                                "title": "WondLa",
                                "thumbnail_url": "https://cdn.animationexplore.com/catimg/933627.jpg"
                            },
                            {
                                "url": "{\"title\":\"WondLa\",\"url\":\"/wondla-episode-1-doors\",\"thumbnailUrl\":\"https://cdn.animationexplore.com/catimg/933627.jpg\"}",
                                "title": "WondLa",
                                "thumbnail_url": "https://cdn.animationexplore.com/catimg/933627.jpg"
                            },
                            {
                                "url": "{\"title\":\"Shy Season 2\",\"url\":\"/shy-season-2-episode-1-english-subbed\",\"thumbnailUrl\":\"https://cdn.animationexplore.com/catimg/933167.jpg\"}",
                                "title": "Shy Season 2",
                                "thumbnail_url": "https://cdn.animationexplore.com/catimg/933167.jpg"
                            },
                            {
                                "url": "{\"title\":\"Mission Yozakura Family\",\"url\":\"/mission-yozakura-family-episode-3-english-dubbed\",\"thumbnailUrl\":\"https://cdn.animationexplore.com/catimg/933612.jpg\"}",
                                "title": "Mission Yozakura Family",
                                "thumbnail_url": "https://cdn.animationexplore.com/catimg/933612.jpg"
                            },
                            {
                                "url": "{\"title\":\"The Duke of Death and His Maid Season 3\",\"url\":\"/the-duke-of-death-and-his-maid-season-3-episode-11-english-dubbed\",\"thumbnailUrl\":\"https://cdn.animationexplore.com/catimg/908768.jpg\"}",
                                "title": "The Duke of Death and His Maid Season 3",
                                "thumbnail_url": "https://cdn.animationexplore.com/catimg/908768.jpg"
                            },
                            {
                                "url": "{\"title\":\"Vampire Dormitory\",\"url\":\"/vampire-dormitory-episode-11-english-dubbed\",\"thumbnailUrl\":\"https://cdn.animationexplore.com/catimg/933588.jpg\"}",
                                "title": "Vampire Dormitory",
                                "thumbnail_url": "https://cdn.animationexplore.com/catimg/933588.jpg"
                            }
                        ],
                        "hasNextPage": false
                    }
                ],
                "passed": true
            },
            "search": {
                "error": "eu.kanade.tachiyomi.network.HttpException: HTTP error 403",
                "passed": false
            },
            "details": {
                "result": {
                    "url": "{\"title\":\"Kit n Kate\",\"url\":\"/kit-n-kate-episode-1-me-oh-my-blueberry-pie-mad-mad-mad-time-to-climb-the-catelephant\",\"thumbnailUrl\":\"https://cdn.animationexplore.com/catimg/933628.jpg\"}",
                    "title": "Kit n Kate",
                    "description": "",
                    "genre": "",
                    "thumbnail_url": "https://cdn.animationexplore.com/catimg/933628.jpg",
                    "initialized": true
                },
                "passed": true
            },
            "episodes": {
                "result": [
                    {
                        "url": "/kit-n-kate-episode-13-and-what-if-dressed-to-ill-quiet-time-something-fishy",
                        "name": "Episode: Kit n Kate Episode 13 And What if!? / Dressed to Ill / Quiet Time / Something fishy.",
                        "episode_number": 13.0
                    },
                    {
                        "url": "/kit-n-kate-episode-12-the-pet-set-the-chew-chew-train-now-were-cookin-the-blame-game",
                        "name": "Episode: Kit n Kate Episode 12 The Pet Set / The Chew Chew Train / Now We’re Cookin’ / The Blame Game",
                        "episode_number": 12.0
                    }
                ],
                "passed": true
            },
            "videos": {
                "error": "kotlinx.serialization.json.internal.JsonDecodingException: Unexpected JSON token at offset 1: Expected quotation mark '\"', but had 'o' instead at path: $[0]\nJSON input: [optionKey]",
                "passed": false
            }
        }
    }
]